Workbook
Name SPY_ETF_Stock_Price_History__1: Prices!$A$1:$G$3

Sheet Prices
B2: Prices | M2: Returns | X2: Statistics
A3: Date | B3: SPY | C3: VGK | D3: VWO | E3: IEF | F3: LQD | G3: TIP | H3: VNQ | I3: GLD | J3: DBC | K3: BTC | M3: SPY | N3: VGK | O3: VWO | P3: IEF | Q3: LQD | R3: TIP | S3: VNQ | T3: GLD | U3: DBC | V3: BTC | Y3: SPY | Z3: VGK | AA3: VWO | AB3: IEF | AC3: LQD | AD3: TIP | AE3: VNQ | AF3: GLD | AG3: DBC | AH3: BTC
A4: 43496 | B4: 244.838 | C4: 45.747 | D4: 37.0077 | E4: 101.081 | F4: 109.187 | G4: 104.612 | H4: 73.4013 | I4: 124.75 | J4: 15.279 | K4: 3450.66 | X4: Monthly return | Y4: =AVERAGE(M5:M87) -> 0.013353829 | Z4: =AVERAGE(N5:N87) -> 0.0084964115 | AA4: =AVERAGE(O5:O87) -> 0.0054307927 | AB4: =AVERAGE(P5:P87) -> -0.00033629338 | AC4: =AVERAGE(Q5:Q87) -> 0.00051088612 | AD4: =AVERAGE(R5:R87) -> 0.00079045933 | AE4: =AVERAGE(S5:S87) -> 0.0038919991 | AF4: =AVERAGE(T5:T87) -> 0.01496557 | ... AH4: =AVERAGE(V5:V87) -> 0.057898273
A5: 43524 | B5: 252.811 | C5: 47.1948 | D5: 36.8661 | E5: 100.544 | F5: 108.948 | G5: 104.424 | H5: 73.9095 | I5: 123.99 | J5: 15.712 | K5: 3829.95 | M5: =(B5-B4)/B4 -> 0.03256439 | N5: =(C5-C4)/C4 -> 0.031647977 | O5: =(D5-D4)/D4 -> -0.0038262308 | P5: =(E5-E4)/E4 -> -0.0053125711 | Q5: =(F5-F4)/F4 -> -0.0021889053 | R5: =(G5-G4)/G4 -> -0.001797117 | S5: =(H5-H4)/H4 -> 0.0069235831 | T5: =(I5-I4)/I4 -> -0.0060921844 | ... V5: =(K5-K4)/K4 -> 0.1099181 | X5: equiv. yearly return | Y5: =(1+Y4)^12-1 -> 0.17255535 | Z5: =(1+Z4)^12-1 -> 0.10685896 | AA5: =(1+AA4)^12-1 -> 0.067151757 | AB5: =(1+AB4)^12-1 -> -0.0040280647 | AC5: =(1+AC4)^12-1 -> 0.0061478891 | AD5: =(1+AD4)^12-1 -> 0.0095268593 | AE5: =(1+AE4)^12-1 -> 0.047716818 | AF5: =(1+AF4)^12-1 -> 0.19513158 | ... AH5: =(1+AH4)^12-1 -> 0.96483868
A6: 43555 | B6: 257.355 | C6: 47.5562 | D6: 37.7169 | E6: 103.264 | F6: 112.16 | G6: 106.514 | H6: 77.0306 | I6: 122.01 | J6: 15.653 | K6: 4101.72 | M6: =(B6-B5)/B5 -> 0.017973901 | N6: =(C6-C5)/C5 -> 0.0076576233 | O6: =(D6-D5)/D5 -> 0.023078112 | P6: =(E6-E5)/E5 -> 0.027052833 | Q6: =(F6-F5)/F5 -> 0.029481955 | R6: =(G6-G5)/G5 -> 0.020014556 | S6: =(H6-H5)/H5 -> 0.042228672 | T6: =(I6-I5)/I5 -> -0.01596903 | ... V6: =(K6-K5)/K5 -> 0.070959151 | X6: volatility of monthly returns | Y6: =_xlfn.STDEV.S(M5:M87) -> 0.047649233 | Z6: =_xlfn.STDEV.S(N5:N87) -> 0.052220983 | AA6: =_xlfn.STDEV.S(O5:O87) -> 0.046186392 | AB6: =_xlfn.STDEV.S(P5:P87) -> 0.021051838 | AC6: =_xlfn.STDEV.S(Q5:Q87) -> 0.027482967 | AD6: =_xlfn.STDEV.S(R5:R87) -> 0.017505262 | AE6: =_xlfn.STDEV.S(S5:S87) -> 0.054720964 | AF6: =_xlfn.STDEV.S(T5:T87) -> 0.041946019 | ... AH6: =_xlfn.STDEV.S(V5:V87) -> 0.1995656
A7: 43585 | B7: 267.893 | C7: 49.4197 | D7: 38.5263 | E7: 102.726 | F7: 112.657 | G7: 106.742 | H7: 76.9067 | I7: 121.2 | J7: 15.84 | K7: 5370.57 | M7: =(B7-B6)/B6 -> 0.04094733 | N7: =(C7-C6)/C6 -> 0.039185217 | O7: =(D7-D6)/D6 -> 0.021459876 | P7: =(E7-E6)/E6 -> -0.0052099473 | Q7: =(F7-F6)/F6 -> 0.0044311698 | R7: =(G7-G6)/G6 -> 0.0021405637 | S7: =(H7-H6)/H6 -> -0.0016084517 | T7: =(I7-I6)/I6 -> -0.0066388001 | ... V7: =(K7-K6)/K6 -> 0.30934584 | X7: equiv. yearly volatility | Y7: =SQRT(12)*Y6 -> 0.16506178 | Z7: =SQRT(12)*Z6 -> 0.18089879 | AA7: =SQRT(12)*AA6 -> 0.15999435 | AB7: =SQRT(12)*AB6 -> 0.072925707 | AC7: =SQRT(12)*AC6 -> 0.095203789 | AD7: =SQRT(12)*AD6 -> 0.060640006 | AE7: =SQRT(12)*AE6 -> 0.18955898 | AF7: =SQRT(12)*AF6 -> 0.14530527 | ... AH7: =SQRT(12)*AH6 -> 0.69131553
A8: 43616 | B8: 250.781 | C8: 46.6172 | D8: 36.0672 | E8: 105.853 | F8: 114.478 | G8: 108.583 | H8: 77.0129 | I8: 123.33 | J8: 14.895 | K8: 8431.7 | M8: =(B8-B7)/B7 -> -0.063876249 | N8: =(C8-C7)/C7 -> -0.056708155 | O8: =(D8-D7)/D7 -> -0.063829125 | P8: =(E8-E7)/E7 -> 0.0304402 | Q8: =(F8-F7)/F7 -> 0.016164109 | R8: =(G8-G7)/G7 -> 0.017247194 | S8: =(H8-H7)/H7 -> 0.001380894 | T8: =(I8-I7)/I7 -> 0.017574257 | ... V8: =(K8-K7)/K7 -> 0.56998233
A9: 43646 | B9: 268.246 | C9: 49.5786 | D9: 38.005 | E9: 107.109 | F9: 118.217 | G9: 109.425 | H9: 78.2132 | I9: 133.2 | J9: 15.486 | K9: 12315 | M9: =(B9-B8)/B8 -> 0.069642437 | N9: =(C9-C8)/C8 -> 0.063525909 | O9: =(D9-D8)/D8 -> 0.053727486 | P9: =(E9-E8)/E8 -> 0.011865512 | Q9: =(F9-F8)/F8 -> 0.032661297 | R9: =(G9-G8)/G8 -> 0.0077544367 | S9: =(H9-H8)/H8 -> 0.015585701 | T9: =(I9-I8)/I8 -> 0.08002919 | ... V9: =(K9-K8)/K8 -> 0.46055956
A10: 43677 | B10: 272.294 | C10: 48.2878 | D10: 37.316 | E10: 107.149 | F10: 118.505 | G10: 109.762 | H10: 79.5452 | I10: 133.21 | J10: 15.309 | K10: 10050 | M10: =(B10-B9)/B9 -> 0.015090626 | N10: =(C10-C9)/C9 -> -0.026035427 | O10: =(D10-D9)/D9 -> -0.018129194 | P10: =(E10-E9)/E9 -> 0.00037345134 | Q10: =(F10-F9)/F9 -> 0.0024361978 | R10: =(G10-G9)/G9 -> 0.003079735 | S10: =(H10-H9)/H9 -> 0.017030373 | T10: =(I10-I9)/I9 -> 7.5075075e-05 | ... V10: =(K10-K9)/K9 -> -0.18392205 | X10: Covariances of monthly returns | Y10: SPY | Z10: VGK | AA10: VWO | AB10: IEF | AC10: LQD | AD10: TIP | AE10: VNQ | AF10: GLD | AG10: DBC | AH10: BTC | AJ10: Sylvester's criterion
A11: 43708 | B11: 267.751 | C11: 47.4932 | D11: 36.1009 | E11: 111.403 | F11: 123.11 | G11: 112.327 | H11: 82.5247 | I11: 143.75 | J11: 14.6 | K11: 9578.54 | M11: =(B11-B10)/B10 -> -0.016684172 | N11: =(C11-C10)/C10 -> -0.016455502 | O11: =(D11-D10)/D10 -> -0.03256244 | P11: =(E11-E10)/E10 -> 0.039701724 | Q11: =(F11-F10)/F10 -> 0.03885912 | R11: =(G11-G10)/G10 -> 0.023368743 | S11: =(H11-H10)/H10 -> 0.037456691 | T11: =(I11-I10)/I10 -> 0.079123189 | ... V11: =(K11-K10)/K10 -> -0.046911443 | X11: SPY | Y11: =_xlfn.COVARIANCE.S($M$5:$M$87,M$5:M$87) -> 0.0022704494 | Z11: =_xlfn.COVARIANCE.S($M$5:$M$87,N$5:N$87) -> 0.0020767105 | AA11: =_xlfn.COVARIANCE.S($M$5:$M$87,O$5:O$87) -> 0.0015167281 | AB11: =_xlfn.COVARIANCE.S($M$5:$M$87,P$5:P$87) -> 0.00024655077 | AC11: =_xlfn.COVARIANCE.S($M$5:$M$87,Q$5:Q$87) -> 0.0008681289 | AD11: =_xlfn.COVARIANCE.S($M$5:$M$87,R$5:R$87) -> 0.00048962367 | AE11: =_xlfn.COVARIANCE.S($M$5:$M$87,S$5:S$87) -> 0.0021278402 | AF11: =_xlfn.COVARIANCE.S($M$5:$M$87,T$5:T$87) -> 0.0003152741 | ... AH11: =_xlfn.COVARIANCE.S($M$5:$M$87,V$5:V$87) -> 0.0043833924 | AJ11: =MDETERM($Y$11:Y11) -> 0.0022704494
A12: 43738 | B12: 272.947 | C12: 48.7016 | D12: 36.4324 | E12: 110.067 | F12: 122.185 | G12: 111.089 | H12: 84.1123 | I12: 138.87 | J12: 14.807 | K12: 8271.3 | M12: =(B12-B11)/B11 -> 0.01940609 | N12: =(C12-C11)/C11 -> 0.025443642 | O12: =(D12-D11)/D11 -> 0.0091825966 | P12: =(E12-E11)/E11 -> -0.011992496 | Q12: =(F12-F11)/F11 -> -0.0075136057 | R12: =(G12-G11)/G11 -> -0.011021393 | S12: =(H12-H11)/H11 -> 0.019237877 | T12: =(I12-I11)/I11 -> -0.033947826 | ... V12: =(K12-K11)/K11 -> -0.13647591 | X12: VGK | Y12: {=TRANSPOSE(Z11:AH11)} -> 0.0020767105 | Z12: =_xlfn.COVARIANCE.S($N$5:$N$87,N$5:N$87) -> 0.002727031 | AA12: =_xlfn.COVARIANCE.S($N$5:$N$87,O$5:O$87) -> 0.0018617817 | AB12: =_xlfn.COVARIANCE.S($N$5:$N$87,P$5:P$87) -> 0.00032035324 | AC12: =_xlfn.COVARIANCE.S($N$5:$N$87,Q$5:Q$87) -> 0.00098015515 | AD12: =_xlfn.COVARIANCE.S($N$5:$N$87,R$5:R$87) -> 0.00052070188 | AE12: =_xlfn.COVARIANCE.S($N$5:$N$87,S$5:S$87) -> 0.0022509924 | AF12: =_xlfn.COVARIANCE.S($N$5:$N$87,T$5:T$87) -> 0.0006167478 | AG12: =_xlfn.COVARIANCE.S($N$5:$N$87,U$5:U$87) -> 0.0012565362 | AH12: =_xlfn.COVARIANCE.S($N$5:$N$87,V$5:V$87) -> 0.0034866626 | AK12: =MDETERM($Y$11:Z12) -> 1.8788593e-06
A13: 43769 | B13: 278.985 | C13: 50.5728 | D13: 37.8692 | E13: 110.277 | F13: 122.741 | G13: 111.059 | H13: 85.0599 | I13: 142.43 | J13: 15.092 | K13: 9132.42 | M13: =(B13-B12)/B12 -> 0.022121511 | N13: =(C13-C12)/C12 -> 0.038421736 | O13: =(D13-D12)/D12 -> 0.039437424 | P13: =(E13-E12)/E12 -> 0.0019079288 | Q13: =(F13-F12)/F12 -> 0.0045504767 | R13: =(G13-G12)/G12 -> -0.00027005374 | S13: =(H13-H12)/H12 -> 0.011265891 | T13: =(I13-I12)/I12 -> 0.025635486 | ... V13: =(K13-K12)/K12 -> 0.10410939 | X13: VWO | Y13: 0.0015167281 | Z13: {=TRANSPOSE(AA12:AH12)} -> 0.0018617817 | AA13: =_xlfn.COVARIANCE.S($O$4:$O$87,O$4:O$87) -> 0.0021331828 | AB13: =_xlfn.COVARIANCE.S($O$4:$O$87,P$4:P$87) -> 0.00021122084 | AC13: =_xlfn.COVARIANCE.S($O$4:$O$87,Q$4:Q$87) -> 0.00081478014 | AD13: =_xlfn.COVARIANCE.S($O$4:$O$87,R$4:R$87) -> 0.00036327617 | AE13: =_xlfn.COVARIANCE.S($O$4:$O$87,S$4:S$87) -> 0.0015654872 | AF13: =_xlfn.COVARIANCE.S($O$4:$O$87,T$4:T$87) -> 0.00066915255 | AG13: =_xlfn.COVARIANCE.S($O$4:$O$87,U$4:U$87) -> 0.0011266468 | AH13: =_xlfn.COVARIANCE.S($O$4:$O$87,V$4:V$87) -> 0.0023628252 | AL13: =MDETERM($Y$11:AA13) -> 1.5931104e-09
A14: 43799 | B14: 289.074 | C14: 51.2279 | D14: 38.0589 | E14: 109.519 | F14: 123.319 | G14: 111.376 | H14: 83.9501 | I14: 137.86 | J14: 15.072 | K14: 7757.95 | M14: =(B14-B13)/B13 -> 0.036163235 | N14: =(C14-C13)/C13 -> 0.012953604 | O14: =(D14-D13)/D13 -> 0.005009348 | P14: =(E14-E13)/E13 -> -0.0068736001 | Q14: =(F14-F13)/F13 -> 0.0047091029 | R14: =(G14-G13)/G13 -> 0.0028543387 | S14: =(H14-H13)/H13 -> -0.013047276 | T14: =(I14-I13)/I13 -> -0.032085937 | ... V14: =(K14-K13)/K13 -> -0.15050447 | X14: IEF | Y14: 0.00024655077 | Z14: 0.00032035324 | AA14: {=TRANSPOSE(AB13:AH13)} -> 0.00021122084 | AB14: =_xlfn.COVARIANCE.S($P$4:$P$87,P$4:P$87) -> 0.00044317989 | AC14: =_xlfn.COVARIANCE.S($P$4:$P$87,Q$4:Q$87) -> 0.00045320247 | AD14: =_xlfn.COVARIANCE.S($P$4:$P$87,R$4:R$87) -> 0.00028385848 | AE14: =_xlfn.COVARIANCE.S($P$4:$P$87,S$4:S$87) -> 0.00045466286 | AF14: =_xlfn.COVARIANCE.S($P$4:$P$87,T$4:T$87) -> 0.00032458125 | AG14: =_xlfn.COVARIANCE.S($P$4:$P$87,U$4:U$87) -> -0.00029937042 | AH14: =_xlfn.COVARIANCE.S($P$4:$P$87,V$4:V$87) -> 0.00049748579 | AM14: =MDETERM($Y$11:AB14) -> 6.459494e-13
A15: 43830 | B15: 297.478 | C15: 53.5372 | D15: 40.7513 | E15: 108.494 | F15: 123.985 | G15: 111.762 | H15: 84.596 | I15: 142.9 | J15: 15.95 | K15: 7194.24 | M15: =(B15-B14)/B14 -> 0.029072141 | N15: =(C15-C14)/C14 -> 0.045078951 | O15: =(D15-D14)/D14 -> 0.07074298 | P15: =(E15-E14)/E14 -> -0.0093591066 | Q15: =(F15-F14)/F14 -> 0.0054006276 | R15: =(G15-G14)/G14 -> 0.0034657377 | S15: =(H15-H14)/H14 -> 0.0076938562 | T15: =(I15-I14)/I14 -> 0.036558828 | ... V15: =(K15-K14)/K14 -> -0.072662237 | X15: LQD | Y15: 0.0008681289 | Z15: 0.00098015515 | AA15: 0.00081478014 | AB15: {=TRANSPOSE(AC14:AH14)} -> 0.00045320247 | AC15: =_xlfn.COVARIANCE.S($Q$4:$Q$87,Q$4:Q$87) -> 0.00075531345 | AD15: =_xlfn.COVARIANCE.S($Q$4:$Q$87,R$4:R$87) -> 0.00039641232 | AE15: =_xlfn.COVARIANCE.S($Q$4:$Q$87,S$4:S$87) -> 0.0011004556 | AF15: =_xlfn.COVARIANCE.S($Q$4:$Q$87,T$4:T$87) -> 0.00043838635 | AG15: =_xlfn.COVARIANCE.S($Q$4:$Q$87,U$4:U$87) -> 0.00011272438 | AH15: =_xlfn.COVARIANCE.S($Q$4:$Q$87,V$4:V$87) -> 0.0017126919 | AN15: =MDETERM($Y$11:AC15) -> 5.1080238e-17
A16: 43861 | B16: 297.351 | C16: 51.885 | D16: 38.4975 | E16: 112.269 | F16: 127.008 | G16: 114.159 | H16: 85.634 | I16: 149.33 | J16: 14.58 | K16: 9310.99 | M16: =(B16-B15)/B15 -> -0.00042692233 | N16: =(C16-C15)/C15 -> -0.030860785 | O16: =(D16-D15)/D15 -> -0.055306211 | P16: =(E16-E15)/E15 -> 0.034794551 | Q16: =(F16-F15)/F15 -> 0.024381982 | R16: =(G16-G15)/G15 -> 0.021447361 | S16: =(H16-H15)/H15 -> 0.012270084 | T16: =(I16-I15)/I15 -> 0.044996501 | ... V16: =(K16-K15)/K15 -> 0.29422844 | X16: TIP | Y16: 0.00048962367 | Z16: 0.00052070188 | AA16: 0.00036327617 | AB16: 0.00028385848 | AC16: {=TRANSPOSE(AD15:AH15)} -> 0.00039641232 | AD16: =_xlfn.COVARIANCE.S($R$4:$R$87,R$4:R$87) -> 0.00030643419 | AE16: =_xlfn.COVARIANCE.S($R$4:$R$87,S$4:S$87) -> 0.00064094753 | AF16: =_xlfn.COVARIANCE.S($R$4:$R$87,T$4:T$87) -> 0.00030799929 | AG16: =_xlfn.COVARIANCE.S($R$4:$R$87,U$4:U$87) -> 7.3273513e-05 | AH16: =_xlfn.COVARIANCE.S($R$4:$R$87,V$4:V$87) -> 0.0012091978 | AO16: =MDETERM($Y$11:AD16) -> 3.6643133e-21
A17: 43890 | B17: 273.828 | C17: 47.7548 | D17: 37.131 | E17: 115.586 | F17: 128.411 | G17: 115.198 | H17: 79.6179 | I17: 148.38 | J17: 13.61 | K17: 8620.69 | M17: =(B17-B16)/B16 -> -0.079108528 | N17: =(C17-C16)/C16 -> -0.079602968 | O17: =(D17-D16)/D16 -> -0.035495811 | P17: =(E17-E16)/E16 -> 0.02954511 | Q17: =(F17-F16)/F16 -> 0.011046548 | R17: =(G17-G16)/G16 -> 0.0091013411 | S17: =(H17-H16)/H16 -> -0.070253638 | T17: =(I17-I16)/I16 -> -0.0063617491 | ... V17: =(K17-K16)/K16 -> -0.074138196 | X17: VNQ | Y17: 0.0021278402 | Z17: 0.0022509924 | AA17: 0.0015654872 | AB17: 0.00045466286 | AC17: 0.0011004556 | AD17: {=TRANSPOSE(AE16:AH16)} -> 0.00064094753 | AE17: =_xlfn.COVARIANCE.S($S$4:$S$87,S$4:S$87) -> 0.0029943839 | AF17: =_xlfn.COVARIANCE.S($S$4:$S$87,T$4:T$87) -> 0.00049490851 | AG17: =_xlfn.COVARIANCE.S($S$4:$S$87,U$4:U$87) -> 0.00096027881 | AH17: =_xlfn.COVARIANCE.S($S$4:$S$87,V$4:V$87) -> 0.0043492964 | AP17: =MDETERM($Y$11:AE17) -> 2.6255843e-24
A18: 43921 | B18: 239.64 | C18: 39.8039 | D18: 30.8039 | E18: 119.909 | F18: 119.977 | G18: 113.188 | H18: 64.1776 | I18: 148.05 | J18: 11.25 | K18: 6459.95 | M18: =(B18-B17)/B17 -> -0.1248521 | N18: =(C18-C17)/C17 -> -0.16649426 | O18: =(D18-D17)/D17 -> -0.1703994 | P18: =(E18-E17)/E17 -> 0.037400723 | Q18: =(F18-F17)/F17 -> -0.065679731 | R18: =(G18-G17)/G17 -> -0.01744822 | S18: =(H18-H17)/H17 -> -0.19393001 | T18: =(I18-I17)/I17 -> -0.0022240194 | ... V18: =(K18-K17)/K17 -> -0.25064583 | X18: GLD | Y18: 0.0003152741 | Z18: 0.0006167478 | AA18: 0.00066915255 | AB18: 0.00032458125 | AC18: 0.00043838635 | AD18: 0.00030799929 | AE18: {=TRANSPOSE(AF17:AH17)} -> 0.00049490851 | AF18: =_xlfn.COVARIANCE.S($T$4:$T$87,T$4:T$87) -> 0.0017594685 | AG18: =_xlfn.COVARIANCE.S($T$4:$T$87,U$4:U$87) -> 7.3037439e-05 | AH18: =_xlfn.COVARIANCE.S($T$4:$T$87,V$4:V$87) -> 0.001105891 | AQ18: =MDETERM($Y$11:AF18) -> 3.2937397e-27
A19: 43951 | B19: 270.067 | C19: 42.3688 | D19: 33.2062 | E19: 120.218 | F19: 125.785 | G19: 116.624 | H19: 69.9292 | I19: 158.8 | J19: 10.9 | K19: 8764.24 | M19: =(B19-B18)/B18 -> 0.12696962 | N19: =(C19-C18)/C18 -> 0.064438409 | O19: =(D19-D18)/D18 -> 0.077986878 | P19: =(E19-E18)/E18 -> 0.0025769542 | Q19: =(F19-F18)/F18 -> 0.048409278 | R19: =(G19-G18)/G18 -> 0.030356575 | S19: =(H19-H18)/H18 -> 0.089620054 | T19: =(I19-I18)/I18 -> 0.072610605 | ... V19: =(K19-K18)/K18 -> 0.356704 | X19: DBC | Y19: 0.00097690527 | Z19: 0.0012565362 | AA19: 0.0011266468 | AB19: -0.00029937042 | AC19: 0.00011272438 | AD19: 7.3273513e-05 | AE19: 0.00096027881 | AF19: {=TRANSPOSE(AG18:AH18)} -> 7.3037439e-05 | AG19: =_xlfn.COVARIANCE.S($U$4:$U$87,U$4:U$87) -> 0.0024314902 | AH19: =_xlfn.COVARIANCE.S($U$4:$U$87,V$4:V$87) -> 0.0010456425 | AR19: =MDETERM($Y$11:AG19) -> 3.886177e-30
A20: 43982 | B20: 282.93 | C20: 44.8428 | D20: 34.299 | E20: 120.487 | F20: 128.58 | G20: 117.07 | H20: 71.1413 | I20: 162.91 | J20: 11.78 | K20: 9398.5 | M20: =(B20-B19)/B19 -> 0.047628922 | N20: =(C20-C19)/C19 -> 0.058392024 | O20: =(D20-D19)/D19 -> 0.032909517 | P20: =(E20-E19)/E19 -> 0.0022376017 | Q20: =(F20-F19)/F19 -> 0.022220456 | R20: =(G20-G19)/G19 -> 0.0038242557 | S20: =(H20-H19)/H19 -> 0.017333246 | T20: =(I20-I19)/I19 -> 0.025881612 | ... V20: =(K20-K19)/K19 -> 0.072369082 | X20: BTC | Y20: 0.0043833924 | Z20: 0.0034866626 | AA20: 0.0023628252 | AB20: 0.00049748579 | AC20: 0.0017126919 | AD20: 0.0012091978 | AE20: 0.0043492964 | AF20: 0.001105891 | AG20: =AH19 -> 0.0010456425 | AH20: =_xlfn.COVARIANCE.S($V$4:$V$87,V$4:V$87) -> 0.03982643 | AS20: =MDETERM($Y$11:AH20) -> 1.1358429e-31
A21: 44012 | B21: 287.954 | C21: 46.6054 | D21: 36.5211 | E21: 120.537 | F21: 131.294 | G21: 118.249 | H21: 72.8685 | I21: 167.37 | J21: 12.31 | K21: 9165.9 | M21: =(B21-B20)/B20 -> 0.017757042 | N21: =(C21-C20)/C20 -> 0.039306199 | O21: =(D21-D20)/D20 -> 0.064786145 | P21: =(E21-E20)/E20 -> 0.00041498253 | Q21: =(F21-F20)/F20 -> 0.021107482 | R21: =(G21-G20)/G20 -> 0.010070898 | S21: =(H21-H20)/H20 -> 0.024278443 | T21: =(I21-I20)/I20 -> 0.027377079 | ... V21: =(K21-K20)/K20 -> -0.02474863
A22: 44043 | B22: 304.904 | C22: 48.3081 | D22: 39.6557 | E22: 121.573 | F22: 135.362 | G22: 120.982 | H22: 75.5216 | I22: 185.43 | J22: 12.94 | K22: 11328 | M22: =(B22-B21)/B21 -> 0.058863568 | N22: =(C22-C21)/C21 -> 0.036534393 | O22: =(D22-D21)/D21 -> 0.085829835 | P22: =(E22-E21)/E21 -> 0.0085948713 | Q22: =(F22-F21)/F21 -> 0.030983899 | R22: =(G22-G21)/G21 -> 0.023112246 | S22: =(H22-H21)/H21 -> 0.036409422 | T22: =(I22-I21)/I21 -> 0.10790464 | ... V22: =(K22-K21)/K21 -> 0.23588518
A23: 44074 | B23: 326.189 | C23: 50.3926 | D23: 40.7446 | E23: 120.387 | F23: 132.965 | G23: 122.071 | H23: 75.8549 | I23: 184.83 | J23: 13.54 | K23: 11640 | M23: =(B23-B22)/B22 -> 0.069808858 | N23: =(C23-C22)/C22 -> 0.043150114 | O23: =(D23-D22)/D22 -> 0.027458852 | P23: =(E23-E22)/E22 -> -0.0097554556 | Q23: =(F23-F22)/F22 -> -0.017708072 | R23: =(G23-G22)/G22 -> 0.009001339 | S23: =(H23-H22)/H22 -> 0.0044133069 | T23: =(I23-I22)/I22 -> -0.0032357224 | ... V23: =(K23-K22)/K22 -> 0.027542373
A24: 44104 | B24: 313.977 | C24: 48.8228 | D24: 40.257 | E24: 120.697 | F24: 132.091 | G24: 121.596 | H24: 73.8358 | I24: 177.12 | J24: 13.06 | K24: 10709 | M24: =(B24-B23)/B23 -> -0.037438418 | N24: =(C24-C23)/C23 -> -0.031151399 | O24: =(D24-D23)/D23 -> -0.01196723 | P24: =(E24-E23)/E23 -> 0.0025750289 | Q24: =(F24-F23)/F23 -> -0.0065731583 | R24: =(G24-G23)/G23 -> -0.0038911781 | S24: =(H24-H23)/H23 -> -0.026617924 | T24: =(I24-I23)/I23 -> -0.041714007 | ... V24: =(K24-K23)/K23 -> -0.079982818
A25: 44135 | B25: 306.149 | C25: 46.1781 | D25: 40.7869 | E25: 119.042 | F25: 131.414 | G25: 120.784 | H25: 71.619 | I25: 176.2 | J25: 12.65 | K25: 13637 | M25: =(B25-B24)/B24 -> -0.024931763 | N25: =(C25-C24)/C24 -> -0.054169363 | O25: =(D25-D24)/D24 -> 0.013162928 | P25: =(E25-E24)/E24 -> -0.013712023 | Q25: =(F25-F24)/F24 -> -0.0051252546 | R25: =(G25-G24)/G24 -> -0.0066778512 | S25: =(H25-H24)/H24 -> -0.030023376 | T25: =(I25-I24)/I24 -> -0.0051942186 | ... V25: =(K25-K24)/K24 -> 0.27341488 | X25: Correlations | Y25: SPY | Z25: VGK | AA25: VWO | AB25: IEF | AC25: LQD | AD25: TIP | AE25: VNQ | AF25: GLD | AG25: DBC | AH25: BTC | AM25: Fama/French 3 Factors (Monthly)
A26: 44165 | B26: 339.437 | C26: 53.7484 | D26: 44.2791 | E26: 119.372 | F26: 136.078 | G26: 121.932 | H26: 78.5484 | I26: 166.67 | J26: 13.94 | K26: 19484 | M26: =(B26-B25)/B25 -> 0.10873137 | N26: =(C26-C25)/C25 -> 0.16393702 | O26: =(D26-D25)/D25 -> 0.085620628 | P26: =(E26-E25)/E25 -> 0.0027721308 | Q26: =(F26-F25)/F25 -> 0.035490891 | R26: =(G26-G25)/G25 -> 0.0095045701 | S26: =(H26-H25)/H25 -> 0.096753655 | T26: =(I26-I25)/I25 -> -0.054086266 | ... V26: =(K26-K25)/K25 -> 0.42875999 | X26: SPY | Y26: =CORREL($M$4:$M$87,M$4:M$87) -> 1 | Z26: =CORREL($M$4:$M$87,N$4:N$87) -> 0.83459353 | AA26: =CORREL($M$4:$M$87,O$4:O$87) -> 0.68918815 | AB26: =CORREL($M$4:$M$87,P$4:P$87) -> 0.24578786 | AC26: =CORREL($M$4:$M$87,Q$4:Q$87) -> 0.66292545 | AD26: =CORREL($M$4:$M$87,R$4:R$87) -> 0.58699971 | AE26: =CORREL($M$4:$M$87,S$4:S$87) -> 0.81607365 | AF26: =CORREL($M$4:$M$87,T$4:T$87) -> 0.15773993 | ... AH26: =CORREL($M$4:$M$87,V$4:V$87) -> 0.46096585 | AL26: Date | AM26: RF | AN26: Average Monthly return | AO26: Annualized Return
A27: 44196 | B27: 352.023 | C27: 56.4491 | D27: 46.9339 | E27: 119.003 | F27: 136.009 | G27: 123.121 | H27: 80.6993 | I27: 178.36 | J27: 14.7 | K27: 29152 | M27: =(B27-B26)/B26 -> 0.037079046 | N27: =(C27-C26)/C26 -> 0.050247077 | O27: =(D27-D26)/D26 -> 0.059956052 | P27: =(E27-E26)/E26 -> -0.0030911772 | Q27: =(F27-F26)/F26 -> -0.00050706213 | R27: =(G27-G26)/G26 -> 0.0097513368 | S27: =(H27-H26)/H26 -> 0.027383117 | T27: =(I27-I26)/I26 -> 0.070138597 | ... V27: =(K27-K26)/K26 -> 0.49620201 | X27: VGK | Z27: =CORREL($N$4:$N$87,N$4:N$87) -> 1 | AA27: =CORREL($N$4:$N$87,O$4:O$87) -> 0.77191535 | AB27: =CORREL($N$4:$N$87,P$4:P$87) -> 0.29140302 | AC27: =CORREL($N$4:$N$87,Q$4:Q$87) -> 0.6829457 | AD27: =CORREL($N$4:$N$87,R$4:R$87) -> 0.56960724 | AE27: =CORREL($N$4:$N$87,S$4:S$87) -> 0.78772612 | AF27: =CORREL($N$4:$N$87,T$4:T$87) -> 0.28156056 | AG27: =CORREL($N$4:$N$87,U$4:U$87) -> 0.48797064 | AH27: =CORREL($N$4:$N$87,V$4:V$87) -> 0.33456399 | AL27: 43496 | AM27: 0.21 | AN27: =AVERAGE(AM27:AM108)/100 -> 0.0021049383 | AO27: =((1+AN27)^(12))-1 -> 0.025553751
A28: 44227 | B28: 348.434 | C28: 55.9434 | D28: 48.4053 | E28: 117.698 | F28: 133.532 | G28: 123.447 | H28: 80.7258 | I28: 172.61 | J28: 15.19 | K28: 34569 | M28: =(B28-B27)/B27 -> -0.010195357 | N28: =(C28-C27)/C27 -> -0.0089585131 | O28: =(D28-D27)/D27 -> 0.031350474 | P28: =(E28-E27)/E27 -> -0.01096611 | Q28: =(F28-F27)/F27 -> -0.01821203 | R28: =(G28-G27)/G27 -> 0.0026478018 | S28: =(H28-H27)/H27 -> 0.00032837955 | T28: =(I28-I27)/I27 -> -0.03223817 | ... V28: =(K28-K27)/K27 -> 0.18581915 | X28: VWO | AA28: =CORREL($O$4:$O$87,O$4:O$87) -> 1 | AB28: =CORREL($O$4:$O$87,P$4:P$87) -> 0.21723646 | AC28: =CORREL($O$4:$O$87,Q$4:Q$87) -> 0.64189323 | AD28: =CORREL($O$4:$O$87,R$4:R$87) -> 0.44931846 | AE28: =CORREL($O$4:$O$87,S$4:S$87) -> 0.61941506 | AF28: =CORREL($O$4:$O$87,T$4:T$87) -> 0.34539843 | AG28: =CORREL($O$4:$O$87,U$4:U$87) -> 0.49469495 | AH28: =CORREL($O$4:$O$87,V$4:V$87) -> 0.25634914 | AL28: 43524 | AM28: 0.18
A29: 44255 | B29: 358.13 | C29: 57.3853 | D29: 49.1647 | E29: 114.829 | F29: 130.24 | G29: 121.388 | H29: 83.491 | I29: 161.81 | J29: 16.73 | K29: 46234 | M29: =(B29-B28)/B28 -> 0.027827365 | N29: =(C29-C28)/C28 -> 0.025774265 | O29: =(D29-D28)/D28 -> 0.015688365 | P29: =(E29-E28)/E28 -> -0.024375945 | Q29: =(F29-F28)/F28 -> -0.024653267 | R29: =(G29-G28)/G28 -> -0.016679223 | S29: =(H29-H28)/H28 -> 0.034254229 | T29: =(I29-I28)/I28 -> -0.062568797 | ... V29: =(K29-K28)/K28 -> 0.33744106 | X29: IEF | AB29: =CORREL($P$4:$P$87,P$4:P$87) -> 1 | AC29: =CORREL($P$4:$P$87,Q$4:Q$87) -> 0.78331896 | AD29: =CORREL($P$4:$P$87,R$4:R$87) -> 0.77027045 | AE29: =CORREL($P$4:$P$87,S$4:S$87) -> 0.39468054 | AF29: =CORREL($P$4:$P$87,T$4:T$87) -> 0.3675722 | AG29: =CORREL($P$4:$P$87,U$4:U$87) -> -0.2883916 | AH29: =CORREL($P$4:$P$87,V$4:V$87) -> 0.11841452 | AL29: 43555 | AM29: 0.19
A30: 44286 | B30: 374.391 | C30: 59.2894 | D30: 48.8148 | E30: 112.02 | F30: 128.062 | G30: 121.061 | H30: 87.7957 | I30: 159.96 | J30: 16.61 | K30: 58962 | M30: =(B30-B29)/B29 -> 0.0454053 | N30: =(C30-C29)/C29 -> 0.033180971 | O30: =(D30-D29)/D29 -> -0.0071168948 | P30: =(E30-E29)/E29 -> -0.024462462 | Q30: =(F30-F29)/F29 -> -0.016722973 | R30: =(G30-G29)/G29 -> -0.0026938412 | S30: =(H30-H29)/H29 -> 0.051558851 | T30: =(I30-I29)/I29 -> -0.011433162 | ... V30: =(K30-K29)/K29 -> 0.27529524 | X30: LQD | AC30: =CORREL($Q$4:$Q$87,Q$4:Q$87) -> 1 | AD30: =CORREL($Q$4:$Q$87,R$4:R$87) -> 0.82397669 | AE30: =CORREL($Q$4:$Q$87,S$4:S$87) -> 0.73173725 | AF30: =CORREL($Q$4:$Q$87,T$4:T$87) -> 0.38027928 | AG30: =CORREL($Q$4:$Q$87,U$4:U$87) -> 0.083179825 | AH30: =CORREL($Q$4:$Q$87,V$4:V$87) -> 0.31226977 | AL30: 43585 | AM30: 0.21
A31: 44316 | B31: 394.202 | C31: 62.122 | D31: 49.6879 | E31: 113.146 | F31: 129.385 | G31: 122.804 | H31: 94.6974 | I31: 165.66 | J31: 17.91 | K31: 57081 | M31: =(B31-B30)/B30 -> 0.052915268 | N31: =(C31-C30)/C30 -> 0.047775825 | O31: =(D31-D30)/D30 -> 0.017885969 | P31: =(E31-E30)/E30 -> 0.010051776 | Q31: =(F31-F30)/F30 -> 0.010330933 | R31: =(G31-G30)/G30 -> 0.0143977 | S31: =(H31-H30)/H30 -> 0.078610911 | T31: =(I31-I30)/I30 -> 0.035633908 | ... V31: =(K31-K30)/K30 -> -0.031901903 | X31: TIP | AD31: =CORREL($R$4:$R$87,R$4:R$87) -> 1 | AE31: =CORREL($R$4:$R$87,S$4:S$87) -> 0.66911403 | AF31: =CORREL($R$4:$R$87,T$4:T$87) -> 0.41945981 | AG31: =CORREL($R$4:$R$87,U$4:U$87) -> 0.084887187 | AH31: =CORREL($R$4:$R$87,V$4:V$87) -> 0.34613304 | AL31: 43616 | AM31: 0.21
A32: 44347 | B32: 396.787 | C32: 64.8886 | D32: 50.5301 | E32: 113.554 | F32: 129.932 | G32: 123.537 | H32: 95.4622 | I32: 178.38 | J32: 18.6 | K32: 36885 | M32: =(B32-B31)/B31 -> 0.0065575517 | N32: =(C32-C31)/C31 -> 0.044534947 | O32: =(D32-D31)/D31 -> 0.016949801 | P32: =(E32-E31)/E31 -> 0.0036059604 | Q32: =(F32-F31)/F31 -> 0.0042276925 | R32: =(G32-G31)/G31 -> 0.0059688609 | S32: =(H32-H31)/H31 -> 0.0080762513 | T32: =(I32-I31)/I31 -> 0.076783774 | ... V32: =(K32-K31)/K31 -> -0.353813 | X32: VNQ | AE32: =CORREL($S$4:$S$87,S$4:S$87) -> 1 | AF32: =CORREL($S$4:$S$87,T$4:T$87) -> 0.21561573 | AG32: =CORREL($S$4:$S$87,U$4:U$87) -> 0.35588309 | AH32: =CORREL($S$4:$S$87,V$4:V$87) -> 0.39827182 | AL32: 43646 | AM32: 0.18
A33: 44377 | B33: 405.687 | C33: 63.9971 | D33: 51.2017 | E33: 114.63 | F33: 132.557 | G33: 123.774 | H33: 97.9778 | I33: 165.63 | J33: 19.25 | K33: 34796 | M33: =(B33-B32)/B32 -> 0.02243017 | N33: =(C33-C32)/C32 -> -0.013738931 | O33: =(D33-D32)/D32 -> 0.013291088 | P33: =(E33-E32)/E32 -> 0.009475668 | Q33: =(F33-F32)/F32 -> 0.020202875 | R33: =(G33-G32)/G32 -> 0.0019184536 | S33: =(H33-H32)/H32 -> 0.026351792 | T33: =(I33-I32)/I32 -> -0.071476623 | ... V33: =(K33-K32)/K32 -> -0.056635489 | X33: GLD | AF33: =CORREL($T$4:$T$87,T$4:T$87) -> 1 | AG33: =CORREL($T$4:$T$87,U$4:U$87) -> 0.035311692 | AH33: =CORREL($T$4:$T$87,V$4:V$87) -> 0.13211006 | AL33: 43677 | AM33: 0.19
A34: 44408 | B34: 415.592 | C34: 65.188 | D34: 48.1847 | E34: 116.921 | F34: 134.428 | G34: 127.092 | H34: 102.313 | I34: 169.82 | J34: 19.5 | K34: 39920 | M34: =(B34-B33)/B33 -> 0.024415374 | N34: =(C34-C33)/C33 -> 0.018608656 | O34: =(D34-D33)/D33 -> -0.058923825 | P34: =(E34-E33)/E33 -> 0.019986042 | Q34: =(F34-F33)/F33 -> 0.014114683 | R34: =(G34-G33)/G33 -> 0.026806922 | S34: =(H34-H33)/H33 -> 0.044246758 | T34: =(I34-I33)/I33 -> 0.02529735 | ... V34: =(K34-K33)/K33 -> 0.14725831 | X34: DBC | AG34: =CORREL($U$4:$U$87,U$4:U$87) -> 1 | AH34: =CORREL($U$4:$U$87,V$4:V$87) -> 0.10625791 | AL34: 43708 | AM34: 0.16
A35: 44439 | B35: 427.968 | C35: 66.3674 | D35: 49.2408 | E35: 116.383 | F35: 133.741 | G35: 126.121 | H35: 104.525 | I35: 169.69 | J35: 19.18 | K35: 46979 | M35: =(B35-B34)/B34 -> 0.029779207 | N35: =(C35-C34)/C34 -> 0.018092287 | O35: =(D35-D34)/D34 -> 0.021917746 | P35: =(E35-E34)/E34 -> -0.0046013975 | Q35: =(F35-F34)/F34 -> -0.0051105424 | R35: =(G35-G34)/G34 -> -0.0076401347 | S35: =(H35-H34)/H34 -> 0.021619931 | T35: =(I35-I34)/I34 -> -0.00076551643 | ... V35: =(K35-K34)/K34 -> 0.17682866 | X35: BTC | AH35: =CORREL($V$4:$V$87,V$4:V$87) -> 1 | AL35: 43738 | AM35: 0.18
A36: 44469 | B36: 408.012 | C36: 62.7877 | D36: 47.5824 | E36: 114.44 | F36: 131.494 | G36: 124.279 | H36: 98.5774 | I36: 164.22 | J36: 20.18 | K36: 43752 | M36: =(B36-B35)/B35 -> -0.046629655 | N36: =(C36-C35)/C35 -> -0.053937626 | O36: =(D36-D35)/D35 -> -0.033679388 | P36: =(E36-E35)/E35 -> -0.016694878 | Q36: =(F36-F35)/F35 -> -0.016801131 | R36: =(G36-G35)/G35 -> -0.014605022 | S36: =(H36-H35)/H35 -> -0.05690122 | T36: =(I36-I35)/I35 -> -0.032235253 | ... V36: =(K36-K35)/K35 -> -0.068690266 | AL36: 43769 | AM36: 0.15
A37: 44500 | B37: 436.649 | C37: 65.9458 | D37: 48.2 | E37: 113.942 | F37: 132.189 | G37: 125.656 | H37: 105.616 | I37: 166.65 | J37: 21.35 | K37: 62629 | M37: =(B37-B36)/B36 -> 0.070186661 | N37: =(C37-C36)/C36 -> 0.050298068 | O37: =(D37-D36)/D36 -> 0.012979589 | P37: =(E37-E36)/E36 -> -0.0043516253 | Q37: =(F37-F36)/F36 -> 0.0052854123 | R37: =(G37-G36)/G36 -> 0.011079909 | S37: =(H37-H36)/H36 -> 0.071401761 | T37: =(I37-I36)/I36 -> 0.014797223 | ... V37: =(K37-K36)/K36 -> 0.43145456 | AL37: 43799 | AM37: 0.12
A38: 44530 | B38: 433.135 | C38: 62.7209 | D38: 46.8028 | E38: 115.098 | F38: 131.782 | G38: 126.616 | H38: 103.384 | I38: 165.5 | J38: 19.48 | K38: 57330 | M38: =(B38-B37)/B37 -> -0.0080476538 | N38: =(C38-C37)/C37 -> -0.04890228 | O38: =(D38-D37)/D37 -> -0.028987552 | P38: =(E38-E37)/E37 -> 0.010145513 | Q38: =(F38-F37)/F37 -> -0.0030789249 | R38: =(G38-G37)/G37 -> 0.0076399058 | S38: =(H38-H37)/H37 -> -0.021133162 | T38: =(I38-I37)/I37 -> -0.0069006901 | ... V38: =(K38-K37)/K37 -> -0.084609366 | AL38: 43830 | AM38: 0.14
A39: 44561 | B39: 453.169 | C39: 65.9817 | D39: 47.5226 | E39: 114.41 | F39: 131.504 | G39: 126.953 | H39: 113.421 | I39: 170.96 | J39: 20.78 | K39: 47019 | M39: =(B39-B38)/B38 -> 0.046253478 | N39: =(C39-C38)/C38 -> 0.05198905 | O39: =(D39-D38)/D38 -> 0.015379422 | P39: =(E39-E38)/E38 -> -0.0059775148 | Q39: =(F39-F38)/F38 -> -0.0021095446 | R39: =(G39-G38)/G38 -> 0.002661591 | S39: =(H39-H38)/H38 -> 0.097084655 | T39: =(I39-I38)/I38 -> 0.032990937 | ... V39: =(K39-K38)/K38 -> -0.17985348 | X39: Covariances of yearly returns | Y39: SPY | Z39: VGK | AA39: VWO | AB39: IEF | AC39: LQD | AD39: TIP | AE39: VNQ | AF39: GLD | AG39: DBC | AH39: BTC | AL39: 43861 | AM39: 0.13
A40: 44592 | B40: 429.269 | C40: 63.6221 | D40: 47.725 | E40: 112 | F40: 126.78 | G40: 124.339 | H40: 103.866 | I40: 168.09 | J40: 22.42 | K40: 38438 | M40: =(B40-B39)/B39 -> -0.052739706 | N40: =(C40-C39)/C39 -> -0.035761431 | O40: =(D40-D39)/D39 -> 0.0042590262 | P40: =(E40-E39)/E39 -> -0.021064592 | Q40: =(F40-F39)/F39 -> -0.035922862 | R40: =(G40-G39)/G39 -> -0.020590297 | S40: =(H40-H39)/H39 -> -0.084243659 | T40: =(I40-I39)/I39 -> -0.016787553 | ... V40: =(K40-K39)/K39 -> -0.18250069 | X40: SPY | Y40: {=12*Y11:AH20} -> 0.027245392 | Z40: 0.024920526 | AA40: 0.018200738 | AB40: 0.0029586092 | AC40: 0.010417547 | AD40: 0.005875484 | AE40: 0.025534082 | AF40: 0.0037832892 | AG40: 0.011722863 | AH40: 0.052600708 | AL40: 43890 | AM40: 0.12
A41: 44620 | B41: 416.598 | C41: 60.2575 | D41: 45.9471 | E41: 111.551 | F41: 123.836 | G41: 124.963 | H41: 100.248 | I41: 178.38 | J41: 23.87 | K41: 43107 | M41: =(B41-B40)/B40 -> -0.029517622 | N41: =(C41-C40)/C40 -> -0.052884139 | O41: =(D41-D40)/D40 -> -0.037253012 | P41: =(E41-E40)/E40 -> -0.0040089286 | Q41: =(F41-F40)/F40 -> -0.023221328 | R41: =(G41-G40)/G40 -> 0.005018538 | S41: =(H41-H40)/H40 -> -0.034833343 | T41: =(I41-I40)/I40 -> 0.061217205 | ... V41: =(K41-K40)/K40 -> 0.12146834 | X41: VGK | Y41: 0.024920526 | Z41: 0.032724373 | AA41: 0.02234138 | AB41: 0.0038442389 | AC41: 0.011761862 | AD41: 0.0062484226 | AE41: 0.027011909 | AF41: 0.0074009737 | AG41: 0.015078434 | AH41: 0.041839951 | AL41: 43921 | AM41: 0.12
A42: 44651 | B42: 432.267 | C42: 60.3525 | D42: 44.4517 | E42: 106.919 | F42: 120.007 | G42: 122.398 | H42: 106.53 | I42: 180.65 | J42: 26.06 | K42: 45775 | M42: =(B42-B41)/B41 -> 0.037611798 | N42: =(C42-C41)/C41 -> 0.0015765672 | O42: =(D42-D41)/D41 -> -0.032546124 | P42: =(E42-E41)/E41 -> -0.041523608 | Q42: =(F42-F41)/F41 -> -0.030919926 | R42: =(G42-G41)/G41 -> -0.020526076 | S42: =(H42-H41)/H41 -> 0.062664592 | T42: =(I42-I41)/I41 -> 0.012725642 | ... V42: =(K42-K41)/K41 -> 0.0618925 | X42: VWO | Y42: 0.018200738 | Z42: 0.02234138 | AA42: 0.025598193 | AB42: 0.0025346501 | AC42: 0.0097773617 | AD42: 0.004359314 | AE42: 0.018785847 | AF42: 0.0080298306 | AG42: 0.013519761 | AH42: 0.028353902 | AL42: 43951 | AM42: 0
A43: 44681 | B43: 394.327 | C43: 56.5829 | D43: 41.8595 | E43: 102.287 | F43: 111.733 | G43: 118.962 | H43: 102.175 | I43: 176.91 | J43: 27.53 | K43: 38322 | M43: =(B43-B42)/B42 -> -0.087769827 | N43: =(C43-C42)/C42 -> -0.062459716 | O43: =(D43-D42)/D42 -> -0.05831498 | P43: =(E43-E42)/E42 -> -0.043322515 | Q43: =(F43-F42)/F42 -> -0.068945978 | R43: =(G43-G42)/G42 -> -0.028072354 | S43: =(H43-H42)/H42 -> -0.040880503 | T43: =(I43-I42)/I42 -> -0.020703017 | ... V43: =(K43-K42)/K42 -> -0.16281813 | X43: IEF | Y43: 0.0029586092 | Z43: 0.0038442389 | AA43: 0.0025346501 | AB43: 0.0053181587 | AC43: 0.0054384297 | AD43: 0.0034063017 | AE43: 0.0054559543 | AF43: 0.003894975 | AG43: -0.0035924451 | AH43: 0.0059698295 | AL43: 43982 | AM43: 0.01
A44: 44712 | B44: 395.216 | C44: 57.9492 | D44: 42.0522 | E44: 102.924 | F44: 113.811 | G44: 117.783 | H44: 97.388 | I44: 171.14 | J44: 28.8 | K44: 31672.9 | M44: =(B44-B43)/B43 -> 0.0022544741 | N44: =(C44-C43)/C43 -> 0.024146871 | O44: =(D44-D43)/D43 -> 0.004603495 | P44: =(E44-E43)/E43 -> 0.0062275754 | Q44: =(F44-F43)/F43 -> 0.018597908 | R44: =(G44-G43)/G43 -> -0.0099107278 | S44: =(H44-H43)/H43 -> -0.046850991 | T44: =(I44-I43)/I43 -> -0.032615454 | ... V44: =(K44-K43)/K43 -> -0.17350608 | X44: LQD | Y44: 0.010417547 | Z44: 0.011761862 | AA44: 0.0097773617 | AB44: 0.0054384297 | AC44: 0.0090637614 | AD44: 0.0047569479 | AE44: 0.013205467 | AF44: 0.0052606362 | AG44: 0.0013526926 | AH44: 0.020552303 | AL44: 44012 | AM44: 0.01
A45: 44742 | B45: 362.629 | C45: 52.2134 | D45: 40.4331 | E45: 101.909 | F45: 109.425 | G45: 112.802 | H45: 90.1337 | I45: 168.46 | J45: 26.64 | K45: 18797.2 | M45: =(B45-B44)/B44 -> -0.082453646 | N45: =(C45-C44)/C44 -> -0.098979796 | O45: =(D45-D44)/D44 -> -0.038502147 | P45: =(E45-E44)/E44 -> -0.0098616455 | Q45: =(F45-F44)/F44 -> -0.038537575 | R45: =(G45-G44)/G44 -> -0.042289634 | S45: =(H45-H44)/H44 -> -0.074488643 | T45: =(I45-I44)/I44 -> -0.015659694 | ... V45: =(K45-K44)/K44 -> -0.40652103 | X45: TIP | Y45: 0.005875484 | Z45: 0.0062484226 | AA45: 0.004359314 | AB45: 0.0034063017 | AC45: 0.0047569479 | AD45: 0.0036772103 | AE45: 0.0076913704 | AF45: 0.0036959915 | AG45: 0.00087928216 | AH45: 0.014510374 | AL45: 44043 | AM45: 0.01
A46: 44773 | B46: 396.023 | C46: 54.8232 | D46: 40.1127 | E46: 104.768 | F46: 113.98 | G46: 117.08 | H46: 97.8995 | I46: 164.1 | J46: 26.11 | K46: 23908.8 | M46: =(B46-B45)/B45 -> 0.092088608 | N46: =(C46-C45)/C45 -> 0.049983338 | O46: =(D46-D45)/D45 -> -0.0079242007 | P46: =(E46-E45)/E45 -> 0.028054441 | Q46: =(F46-F45)/F45 -> 0.041626685 | R46: =(G46-G45)/G45 -> 0.037924859 | S46: =(H46-H45)/H45 -> 0.086158673 | T46: =(I46-I45)/I45 -> -0.025881515 | ... V46: =(K46-K45)/K45 -> 0.27193412 | X46: VNQ | Y46: 0.025534082 | Z46: 0.027011909 | AA46: 0.018785847 | AB46: 0.0054559543 | AC46: 0.013205467 | AD46: 0.0076913704 | AE46: 0.035932606 | AF46: 0.0059389022 | AG46: 0.011523346 | AH46: 0.052191556 | AL46: 44074 | AM46: 0.01
A47: 44804 | B47: 379.865 | C47: 50.7306 | D47: 39.9283 | E47: 100.726 | F47: 108.936 | G47: 113.91 | H47: 92.0133 | I47: 159.27 | J47: 25.72 | K47: 20286.3 | M47: =(B47-B46)/B46 -> -0.040800661 | N47: =(C47-C46)/C46 -> -0.074650878 | O47: =(D47-D46)/D46 -> -0.0045970478 | P47: =(E47-E46)/E46 -> -0.038580483 | Q47: =(F47-F46)/F46 -> -0.044253378 | R47: =(G47-G46)/G46 -> -0.027075504 | S47: =(H47-H46)/H46 -> -0.060124924 | T47: =(I47-I46)/I46 -> -0.029433272 | ... V47: =(K47-K46)/K46 -> -0.15151325 | X47: GLD | Y47: 0.0037832892 | Z47: 0.0074009737 | AA47: 0.0080298306 | AB47: 0.003894975 | AC47: 0.0052606362 | AD47: 0.0036959915 | AE47: 0.0059389022 | AF47: 0.021113622 | AG47: 0.00087644927 | AH47: 0.013270692 | AL47: 44104 | AM47: 0.01
A48: 44834 | B48: 344.75 | C48: 45.8193 | D48: 35.9035 | E48: 95.7867 | F48: 102.137 | G48: 104.9 | H48: 80.17 | I48: 154.67 | J48: 23.91 | K48: 19473.3 | M48: =(B48-B47)/B47 -> -0.092440736 | N48: =(C48-C47)/C47 -> -0.096811392 | O48: =(D48-D47)/D47 -> -0.10080069 | P48: =(E48-E47)/E47 -> -0.049036991 | Q48: =(F48-F47)/F47 -> -0.062412793 | R48: =(G48-G47)/G47 -> -0.079097533 | S48: =(H48-H47)/H47 -> -0.12871291 | T48: =(I48-I47)/I47 -> -0.028881773 | ... V48: =(K48-K47)/K47 -> -0.040076308 | X48: DBC | Y48: 0.011722863 | Z48: 0.015078434 | AA48: 0.013519761 | AB48: -0.0035924451 | AC48: 0.0013526926 | AD48: 0.00087928216 | AE48: 0.011523346 | AF48: 0.00087644927 | AG48: 0.029177883 | AH48: 0.01254771 | AL48: 44135 | AM48: 0.01
A49: 44865 | B49: 372.772 | C49: 49.6814 | D49: 34.8803 | E49: 94.21 | F49: 101.04 | G49: 106.39 | H49: 82.98 | I49: 151.91 | J49: 25.12 | K49: 20473.3 | M49: =(B49-B48)/B48 -> 0.081282088 | N49: =(C49-C48)/C48 -> 0.084289808 | O49: =(D49-D48)/D48 -> -0.028498614 | P49: =(E49-E48)/E48 -> -0.016460532 | Q49: =(F49-F48)/F48 -> -0.010740476 | R49: =(G49-G48)/G48 -> 0.014204004 | S49: =(H49-H48)/H48 -> 0.035050518 | T49: =(I49-I48)/I48 -> -0.017844443 | ... V49: =(K49-K48)/K48 -> 0.051352365 | X49: BTC | Y49: 0.052600708 | Z49: 0.041839951 | AA49: 0.028353902 | AB49: 0.0059698295 | AC49: 0.020552303 | AD49: 0.014510374 | AE49: 0.052191556 | AF49: 0.013270692 | AG49: 0.01254771 | AH49: 0.47791716 | AL49: 44165 | AM49: 0.01
A50: 44895 | B50: 393.496 | C50: 56.383 | D50: 39.8688 | E50: 97.61 | F50: 107.76 | G50: 108.34 | H50: 88.08 | I50: 164.81 | J50: 25.49 | K50: 17158.1 | M50: =(B50-B49)/B49 -> 0.055594304 | N50: =(C50-C49)/C49 -> 0.13489153 | O50: =(D50-D49)/D49 -> 0.14301769 | P50: =(E50-E49)/E49 -> 0.036089587 | Q50: =(F50-F49)/F49 -> 0.066508314 | R50: =(G50-G49)/G49 -> 0.01832879 | S50: =(H50-H49)/H49 -> 0.061460593 | T50: =(I50-I49)/I49 -> 0.084918702 | ... V50: =(K50-K49)/K49 -> -0.16192797 | AL50: 44196 | AM50: 0.01
A51: 44926 | B51: 370.819 | C51: 55.44 | D51: 38.98 | E51: 95.78 | F51: 105.43 | G51: 106.44 | H51: 82.48 | I51: 169.64 | J51: 24.65 | K51: 16590.7 | M51: =(B51-B50)/B50 -> -0.057629557 | N51: =(C51-C50)/C50 -> -0.016724899 | O51: =(D51-D50)/D50 -> -0.022293121 | P51: =(E51-E50)/E50 -> -0.018748079 | Q51: =(F51-F50)/F50 -> -0.021622123 | R51: =(G51-G50)/G50 -> -0.017537382 | S51: =(H51-H50)/H50 -> -0.063578565 | T51: =(I51-I50)/I50 -> 0.029306474 | ... V51: =(K51-K50)/K50 -> -0.03306893 | AL51: 44227 | AM51: 0
A52: 44957 | B52: 394.139 | C52: 60.74 | D52: 42.23 | E52: 99.21 | F52: 110.87 | G52: 108.65 | H52: 91.06 | I52: 179.41 | J52: 24.87 | K52: 23181.8 | M52: =(B52-B51)/B51 -> 0.062887824 | N52: =(C52-C51)/C51 -> 0.095598846 | O52: =(D52-D51)/D51 -> 0.08337609 | P52: =(E52-E51)/E51 -> 0.035811234 | Q52: =(F52-F51)/F51 -> 0.051598217 | R52: =(G52-G51)/G51 -> 0.020762871 | S52: =(H52-H51)/H51 -> 0.10402522 | T52: =(I52-I51)/I51 -> 0.057592549 | ... V52: =(K52-K51)/K51 -> 0.39727679 | AL52: 44255 | AM52: 0
A53: 44985 | B53: 384.227 | C53: 59.7 | D53: 39.42 | E53: 95.76 | F53: 105.92 | G53: 107.18 | H53: 85.72 | I53: 169.78 | J53: 23.76 | K53: 23158.9 | M53: =(B53-B52)/B52 -> -0.025148488 | N53: =(C53-C52)/C52 -> -0.01712216 | O53: =(D53-D52)/D52 -> -0.066540374 | P53: =(E53-E52)/E52 -> -0.03477472 | Q53: =(F53-F52)/F52 -> -0.044646884 | R53: =(G53-G52)/G52 -> -0.013529682 | S53: =(H53-H52)/H52 -> -0.058642653 | T53: =(I53-I52)/I52 -> -0.053675938 | ... V53: =(K53-K52)/K52 -> -0.00098784391 | AL53: 44286 | AM53: 0
A54: 45016 | B54: 398.475 | C54: 60.95 | D54: 40.4 | E54: 99.12 | F54: 109.61 | G54: 110.25 | H54: 83.04 | I54: 183.22 | J54: 23.74 | K54: 28441.6 | M54: =(B54-B53)/B53 -> 0.037082246 | N54: =(C54-C53)/C53 -> 0.020938023 | O54: =(D54-D53)/D53 -> 0.024860477 | P54: =(E54-E53)/E53 -> 0.035087719 | Q54: =(F54-F53)/F53 -> 0.034837613 | R54: =(G54-G53)/G53 -> 0.028643404 | S54: =(H54-H53)/H53 -> -0.031264582 | T54: =(I54-I53)/I53 -> 0.079161268 | ... V54: =(K54-K53)/K53 -> 0.22810669 | AL54: 44316 | AM54: 0
A55: 45046 | B55: 404.841 | C55: 63.47 | D55: 40.24 | E55: 99.73 | F55: 109.93 | G55: 110.18 | H55: 83.3 | I55: 184.8 | J55: 23.56 | K55: 29351.3 | M55: =(B55-B54)/B54 -> 0.015975908 | N55: =(C55-C54)/C54 -> 0.041345365 | O55: =(D55-D54)/D54 -> -0.003960396 | P55: =(E55-E54)/E54 -> 0.0061541566 | Q55: =(F55-F54)/F54 -> 0.0029194417 | R55: =(G55-G54)/G54 -> -0.00063492063 | S55: =(H55-H54)/H54 -> 0.0031310212 | T55: =(I55-I54)/I54 -> 0.0086235127 | ... V55: =(K55-K54)/K54 -> 0.031984839 | AL55: 44347 | AM55: 0
A56: 45077 | B56: 406.709 | C56: 60.22 | D56: 39.05 | E56: 98.06 | F56: 107.62 | G56: 108.3 | H56: 80 | I56: 182.32 | J56: 22.05 | K56: 27095.1 | M56: =(B56-B55)/B55 -> 0.0046141572 | N56: =(C56-C55)/C55 -> -0.051205294 | O56: =(D56-D55)/D55 -> -0.029572565 | P56: =(E56-E55)/E55 -> -0.016745212 | Q56: =(F56-F55)/F55 -> -0.021013372 | R56: =(G56-G55)/G55 -> -0.017062988 | S56: =(H56-H55)/H55 -> -0.039615846 | T56: =(I56-I55)/I55 -> -0.013419913 | ... V56: =(K56-K55)/K55 -> -0.076868827 | AL56: 44377 | AM56: 0
A57: 45107 | B57: 433.065 | C57: 61.7 | D57: 40.68 | E57: 96.6 | F57: 108.14 | G57: 107.62 | H57: 83.56 | I57: 178.27 | J57: 22.7 | K57: 30377.2 | M57: =(B57-B56)/B56 -> 0.06480309 | N57: =(C57-C56)/C56 -> 0.024576553 | O57: =(D57-D56)/D56 -> 0.041741357 | P57: =(E57-E56)/E56 -> -0.014888844 | Q57: =(F57-F56)/F56 -> 0.0048318156 | R57: =(G57-G56)/G56 -> -0.006278855 | S57: =(H57-H56)/H56 -> 0.0445 | T57: =(I57-I56)/I56 -> -0.02221369 | ... V57: =(K57-K56)/K56 -> 0.1211326 | AL57: 44408 | AM57: 0
A58: 45138 | B58: 447.241 | C58: 63.49 | D58: 43.07 | E58: 95.74 | F58: 107.85 | G58: 107.16 | H58: 85.26 | I58: 182.35 | J58: 24.68 | K58: 29238.3 | M58: =(B58-B57)/B57 -> 0.032734116 | N58: =(C58-C57)/C57 -> 0.029011345 | O58: =(D58-D57)/D57 -> 0.058751229 | P58: =(E58-E57)/E57 -> -0.0089026915 | Q58: =(F58-F57)/F57 -> -0.0026817089 | R58: =(G58-G57)/G57 -> -0.0042742985 | S58: =(H58-H57)/H57 -> 0.020344663 | T58: =(I58-I57)/I57 -> 0.022886633 | ... V58: =(K58-K57)/K57 -> -0.037491935 | AL58: 44439 | AM58: 0
A59: 45169 | B59: 439.972 | C59: 60.92 | D59: 40.53 | E59: 94.8 | F59: 106.16 | G59: 106.07 | H59: 82.38 | I59: 180.02 | J59: 24.59 | K59: 25988.8 | M59: =(B59-B58)/B58 -> -0.016252982 | N59: =(C59-C58)/C58 -> -0.040478816 | O59: =(D59-D58)/D58 -> -0.058973764 | P59: =(E59-E58)/E58 -> -0.0098182578 | Q59: =(F59-F58)/F58 -> -0.015669912 | R59: =(G59-G58)/G58 -> -0.010171706 | S59: =(H59-H58)/H58 -> -0.033779029 | T59: =(I59-I58)/I58 -> -0.012777625 | ... V59: =(K59-K58)/K58 -> -0.11113847 | AL59: 44469 | AM59: 0
A60: 45199 | B60: 419.103 | C60: 57.93 | D60: 39.21 | E60: 91.59 | F60: 102.02 | G60: 103.72 | H60: 75.66 | I60: 171.45 | J60: 24.96 | K60: 26918.5 | M60: =(B60-B59)/B59 -> -0.047432564 | N60: =(C60-C59)/C59 -> -0.049080762 | O60: =(D60-D59)/D59 -> -0.032568468 | P60: =(E60-E59)/E59 -> -0.033860759 | Q60: =(F60-F59)/F59 -> -0.038997739 | R60: =(G60-G59)/G59 -> -0.022155181 | S60: =(H60-H59)/H59 -> -0.081573197 | T60: =(I60-I59)/I59 -> -0.047605822 | ... V60: =(K60-K59)/K59 -> 0.035773102 | AL60: 44500 | AM60: 0
A61: 45230 | B61: 410.004 | C61: 56.14 | D61: 37.94 | E61: 89.59 | F61: 99.17 | G61: 102.8 | H61: 72.92 | I61: 184.09 | J61: 24.51 | K61: 34588.5 | M61: =(B61-B60)/B60 -> -0.021710653 | N61: =(C61-C60)/C60 -> -0.030899361 | O61: =(D61-D60)/D60 -> -0.032389697 | P61: =(E61-E60)/E60 -> -0.021836445 | Q61: =(F61-F60)/F60 -> -0.027935699 | R61: =(G61-G60)/G60 -> -0.0088700347 | S61: =(H61-H60)/H60 -> -0.036214644 | T61: =(I61-I60)/I60 -> 0.073724118 | ... V61: =(K61-K60)/K60 -> 0.28493415 | AL61: 44530 | AM61: 0
... A87: 46008 | B87: 671.4 | C87: 82.59 | D87: 53.13 | E87: 96.525 | F87: 110.435 | G87: 110.29 | H87: 89.41 | I87: 399.29 | J87: 22.85 | K87: 86352 | M87: =(B87-B86)/B86 -> -0.017544887 | N87: =(C87-C86)/C86 -> 0.013001349 | O87: =(D87-D86)/D86 -> -0.021546961 | P87: =(E87-E86)/E86 -> -0.01 | Q87: =(F87-F86)/F86 -> -0.012739138 | R87: =(G87-G86)/G86 -> -0.0087183175 | S87: =(H87-H86)/H86 -> -0.021129845 | T87: =(I87-I86)/I86 -> 0.029416314 | ... V87: =(K87-K86)/K86 -> -0.053564696 | AL87: 45322 | AM87: 0.47
AL89: 45382 | AM89: 0.43
AL90: 45412 | AM90: 0.47
AL91: 45443 | AM91: 0.44
AL92: 45473 | AM92: 0.41
AL93: 45504 | AM93: 0.45
AL94: 45535 | AM94: 0.48
AL95: 45565 | AM95: 0.4
AL96: 45596 | AM96: 0.39
AL97: 45626 | AM97: 0.4
AL98: 45657 | AM98: 0.37
AL99: 45688 | AM99: 0.37
AL100: 45716 | AM100: 0.33
... AL108: 45961 | AM108: 0.37

Sheet Efficient Frontier & Specific 
A1: Efficient Frontier (10 assets)
A3: Asset | B3: Expected return | C3: Volatility | E3: Correlations | F3: SPY | G3: VGK | H3: VWO | I3: IEF | J3: LQD | K3: TIP | L3: VNQ | M3: GLD | N3: DBC | O3: BTC | Q3: Covariances of monthly returns | R3: SPY | S3: VGK | T3: VWO | U3: IEF | V3: LQD | W3: TIP | X3: VNQ | Y3: GLD | Z3: DBC | AA3: BTC | AC3: Sylvester's criterion
A4: =Prices!Y$3 -> SPY | B4: =Prices!Y4 -> 0.013353829 | C4: =Prices!Y6 -> 0.047649233 | E4: SPY | F4: =Prices!Y26 -> 1 | G4: =Prices!Z26 -> 0.83459353 | H4: =Prices!AA26 -> 0.68918815 | I4: =Prices!AB26 -> 0.24578786 | J4: =Prices!AC26 -> 0.66292545 | K4: =Prices!AD26 -> 0.58699971 | L4: =Prices!AE26 -> 0.81607365 | M4: =Prices!AF26 -> 0.15773993 | ... O4: =Prices!AH26 -> 0.46096585 | Q4: SPY | R4: =Prices!Y11 -> 0.0022704494 | S4: =Prices!Z11 -> 0.0020767105 | T4: =Prices!AA11 -> 0.0015167281 | U4: =Prices!AB11 -> 0.00024655077 | V4: =Prices!AC11 -> 0.0008681289 | W4: =Prices!AD11 -> 0.00048962367 | X4: =Prices!AE11 -> 0.0021278402 | Y4: =Prices!AF11 -> 0.0003152741 | ... AA4: =Prices!AH11 -> 0.0043833924 | AC4: 0.0022704494
A5: =Prices!Z$3 -> VGK | B5: =Prices!Z4 -> 0.0084964115 | C5: =Prices!Z6 -> 0.052220983 | E5: VGK | G5: =Prices!Z27 -> 1 | H5: =Prices!AA27 -> 0.77191535 | I5: =Prices!AB27 -> 0.29140302 | J5: =Prices!AC27 -> 0.6829457 | K5: =Prices!AD27 -> 0.56960724 | L5: =Prices!AE27 -> 0.78772612 | M5: =Prices!AF27 -> 0.28156056 | N5: =Prices!AG27 -> 0.48797064 | O5: =Prices!AH27 -> 0.33456399 | Q5: VGK | R5: =Prices!Y12 -> 0.0020767105 | S5: =Prices!Z12 -> 0.002727031 | T5: =Prices!AA12 -> 0.0018617817 | U5: =Prices!AB12 -> 0.00032035324 | V5: =Prices!AC12 -> 0.00098015515 | W5: =Prices!AD12 -> 0.00052070188 | X5: =Prices!AE12 -> 0.0022509924 | Y5: =Prices!AF12 -> 0.0006167478 | ... AA5: =Prices!AH12 -> 0.0034866626 | AD5: 1.8788593e-06
A6: =Prices!AA$3 -> VWO | B6: =Prices!AA4 -> 0.0054307927 | C6: =Prices!AA6 -> 0.046186392 | E6: VWO | H6: =Prices!AA28 -> 1 | I6: =Prices!AB28 -> 0.21723646 | J6: =Prices!AC28 -> 0.64189323 | K6: =Prices!AD28 -> 0.44931846 | L6: =Prices!AE28 -> 0.61941506 | M6: =Prices!AF28 -> 0.34539843 | N6: =Prices!AG28 -> 0.49469495 | O6: =Prices!AH28 -> 0.25634914 | Q6: VWO | R6: =Prices!Y13 -> 0.0015167281 | S6: =Prices!Z13 -> 0.0018617817 | T6: =Prices!AA13 -> 0.0021331828 | U6: =Prices!AB13 -> 0.00021122084 | V6: =Prices!AC13 -> 0.00081478014 | W6: =Prices!AD13 -> 0.00036327617 | X6: =Prices!AE13 -> 0.0015654872 | Y6: =Prices!AF13 -> 0.00066915255 | ... AA6: =Prices!AH13 -> 0.0023628252 | AE6: 1.5931104e-09
A7: =Prices!AB$3 -> IEF | B7: =Prices!AB4 -> -0.00033629338 | C7: =Prices!AB6 -> 0.021051838 | E7: IEF | I7: =Prices!AB29 -> 1 | J7: =Prices!AC29 -> 0.78331896 | K7: =Prices!AD29 -> 0.77027045 | L7: =Prices!AE29 -> 0.39468054 | M7: =Prices!AF29 -> 0.3675722 | N7: =Prices!AG29 -> -0.2883916 | O7: =Prices!AH29 -> 0.11841452 | Q7: IEF | R7: =Prices!Y14 -> 0.00024655077 | S7: =Prices!Z14 -> 0.00032035324 | T7: =Prices!AA14 -> 0.00021122084 | U7: =Prices!AB14 -> 0.00044317989 | V7: =Prices!AC14 -> 0.00045320247 | W7: =Prices!AD14 -> 0.00028385848 | X7: =Prices!AE14 -> 0.00045466286 | Y7: =Prices!AF14 -> 0.00032458125 | ... AA7: =Prices!AH14 -> 0.00049748579 | AF7: 6.459494e-13
A8: =Prices!AC$3 -> LQD | B8: =Prices!AC4 -> 0.00051088612 | C8: =Prices!AC6 -> 0.027482967 | E8: LQD | J8: =Prices!AC30 -> 1 | K8: =Prices!AD30 -> 0.82397669 | L8: =Prices!AE30 -> 0.73173725 | M8: =Prices!AF30 -> 0.38027928 | N8: =Prices!AG30 -> 0.083179825 | O8: =Prices!AH30 -> 0.31226977 | Q8: LQD | R8: =Prices!Y15 -> 0.0008681289 | S8: =Prices!Z15 -> 0.00098015515 | T8: =Prices!AA15 -> 0.00081478014 | U8: =Prices!AB15 -> 0.00045320247 | V8: =Prices!AC15 -> 0.00075531345 | W8: =Prices!AD15 -> 0.00039641232 | X8: =Prices!AE15 -> 0.0011004556 | Y8: =Prices!AF15 -> 0.00043838635 | ... AA8: =Prices!AH15 -> 0.0017126919 | AG8: 5.1080238e-17
A9: =Prices!AD$3 -> TIP | B9: =Prices!AD4 -> 0.00079045933 | C9: =Prices!AD6 -> 0.017505262 | E9: TIP | K9: =Prices!AD31 -> 1 | L9: =Prices!AE31 -> 0.66911403 | M9: =Prices!AF31 -> 0.41945981 | N9: =Prices!AG31 -> 0.084887187 | O9: =Prices!AH31 -> 0.34613304 | Q9: TIP | R9: =Prices!Y16 -> 0.00048962367 | S9: =Prices!Z16 -> 0.00052070188 | T9: =Prices!AA16 -> 0.00036327617 | U9: =Prices!AB16 -> 0.00028385848 | V9: =Prices!AC16 -> 0.00039641232 | W9: =Prices!AD16 -> 0.00030643419 | X9: =Prices!AE16 -> 0.00064094753 | Y9: =Prices!AF16 -> 0.00030799929 | ... AA9: =Prices!AH16 -> 0.0012091978 | AH9: 3.6643133e-21
A10: =Prices!AE$3 -> VNQ | B10: =Prices!AE4 -> 0.0038919991 | C10: =Prices!AE6 -> 0.054720964 | E10: VNQ | L10: =Prices!AE32 -> 1 | M10: =Prices!AF32 -> 0.21561573 | N10: =Prices!AG32 -> 0.35588309 | O10: =Prices!AH32 -> 0.39827182 | Q10: VNQ | R10: =Prices!Y17 -> 0.0021278402 | S10: =Prices!Z17 -> 0.0022509924 | T10: =Prices!AA17 -> 0.0015654872 | U10: =Prices!AB17 -> 0.00045466286 | V10: =Prices!AC17 -> 0.0011004556 | W10: =Prices!AD17 -> 0.00064094753 | X10: =Prices!AE17 -> 0.0029943839 | Y10: =Prices!AF17 -> 0.00049490851 | ... AA10: =Prices!AH17 -> 0.0043492964 | AI10: 2.6255843e-24
A11: =Prices!AF$3 -> GLD | B11: =Prices!AF4 -> 0.01496557 | C11: =Prices!AF6 -> 0.041946019 | E11: GLD | M11: =Prices!AF33 -> 1 | N11: =Prices!AG33 -> 0.035311692 | O11: =Prices!AH33 -> 0.13211006 | Q11: GLD | R11: =Prices!Y18 -> 0.0003152741 | S11: =Prices!Z18 -> 0.0006167478 | T11: =Prices!AA18 -> 0.00066915255 | U11: =Prices!AB18 -> 0.00032458125 | V11: =Prices!AC18 -> 0.00043838635 | W11: =Prices!AD18 -> 0.00030799929 | X11: =Prices!AE18 -> 0.00049490851 | Y11: =Prices!AF18 -> 0.0017594685 | ... AA11: =Prices!AH18 -> 0.001105891 | AJ11: 3.2937397e-27
A12: =Prices!AG$3 -> DBC | B12: =Prices!AG4 -> 0.0060828471 | C12: =Prices!AG6 -> 0.049310143 | E12: DBC | N12: =Prices!AG34 -> 1 | O12: =Prices!AH34 -> 0.10625791 | Q12: DBC | R12: =Prices!Y19 -> 0.00097690527 | S12: =Prices!Z19 -> 0.0012565362 | T12: =Prices!AA19 -> 0.0011266468 | U12: =Prices!AB19 -> -0.00029937042 | V12: =Prices!AC19 -> 0.00011272438 | W12: =Prices!AD19 -> 7.3273513e-05 | X12: =Prices!AE19 -> 0.00096027881 | Y12: =Prices!AF19 -> 7.3037439e-05 | ... AA12: =Prices!AH19 -> 0.0010456425 | AK12: 3.886177e-30
A13: =Prices!AH$3 -> BTC | B13: =Prices!AH4 -> 0.057898273 | C13: =Prices!AG6 -> 0.049310143 | E13: BTC | O13: =Prices!AH35 -> 1 | Q13: BTC | R13: =Prices!Y20 -> 0.0043833924 | S13: =Prices!Z20 -> 0.0034866626 | T13: =Prices!AA20 -> 0.0023628252 | U13: =Prices!AB20 -> 0.00049748579 | V13: =Prices!AC20 -> 0.0017126919 | W13: =Prices!AD20 -> 0.0012091978 | X13: =Prices!AE20 -> 0.0043492964 | Y13: =Prices!AF20 -> 0.001105891 | ... AA13: =Prices!AH20 -> 0.03982643 | AL13: 1.1358429e-31
A14: Fama/French 3 Factors (Monthly) | B14: =Prices!AN27/100 -> 2.1049383e-05
A20: COMPUTATIONS using solver
A21: Sum of weights | B21: w1 | C21: w2 | D21: w3 | E21: w4 | F21: w5 | G21: w6 | H21: w7 | I21: w8 | J21: w9 | K21: w10 | L21: variance | M21: volatility | N21: Expected return | O21: Target Expected return | P21: Sharpe ratio
A22: =SUM(B22:K22) -> 1 | B22: 0.32515559 | C22: -0.11020513 | D22: 0.035179565 | E22: 0.82482255 | F22: -0.58849174 | G22: 0.37062519 | H22: -0.17416014 | I22: 0.12364038 | J22: 0.18688846 | K22: 0.0065453069 | L22: {=MMULT(MMULT(B22:K22,R4:AA13),TRANSPOSE(B22:K22))} -> 0.00023482796 | M22: =SQRT(L22) -> 0.015324097 | N22: {=MMULT(B22:K22,B4:B13)} -> 0.006 | O22: 0.006 | P22: =(N22-B14)/M22 -> 0.39016658
A25: PORTFOLIOS
A26: Sum of weights
A27: 0.99999996 | B27: -0.13479043 | C27: -0.071197516 | D27: 0.10762598 | E27: 0.24976097 | F27: -0.11923894 | G27: 1.0800692 | H27: -0.073792211 | I27: -0.15701482 | J27: 0.13735054 | K27: -0.018772748 | L27: 0.00023599389 | M27: 0.015362093 | N27: -0.004
A28: 1 | B28: 0.049188337 | C28: -0.086800884 | D28: 0.078647313 | E28: 0.47978568 | F28: -0.3069397 | G28: 0.79629114 | H28: -0.11393934 | I28: -0.044752713 | J28: 0.15716572 | K28: -0.0086455608 | L28: 0.00018204114 | M28: 0.013492262 | N28: 3.838738e-11
A29: 1.000001 | B29: 0.096395872 | C29: -0.090804633 | D29: 0.071220206 | E29: 0.5388064 | F29: -0.35510273 | G29: 0.72347819 | H29: -0.12424504 | I29: -0.015946034 | J29: 0.16224597 | K29: -0.0060471951 | L29: 0.00017969478 | M29: 0.013405028 | N29: 0.0010263809 | O29: GLOBAL MINIMUM VARIANCE PORTFOLIO
A30: 0.99999975 | B30: 0.18716397 | C30: -0.098499011 | D30: 0.056915462 | E30: 0.65229813 | F30: -0.44771203 | G30: 0.58346715 | H30: -0.14405012 | I30: 0.039440994 | J30: 0.17202523 | K30: -0.0010500189 | L30: 0.00018837618 | M30: 0.01372502 | N30: 0.0029999002
A31: 1 | B31: 0.32515559 | C31: -0.11020513 | D31: 0.035179565 | E31: 0.82482255 | F31: -0.58849174 | G31: 0.37062519 | H31: -0.17416014 | I31: 0.12364038 | J31: 0.18688846 | K31: 0.0065453069 | L31: 0.00023482796 | M31: 0.015324097 | N31: 0.006
A32: 1 | B32: 0.6011231 | C32: -0.13360982 | D32: -0.00828805 | E32: 1.1698576 | F32: -0.87004341 | G32: -0.055039394 | H32: -0.23438054 | I32: 0.29203362 | J32: 0.21661076 | K32: 0.021736115 | L32: 0.00044807392 | M32: 0.021167757 | N32: 0.012
A33: 1 | B33: 0.87709041 | C33: -0.15701483 | D33: -0.051754604 | E33: 1.5148967 | F33: -1.1515976 | G33: -0.48070624 | H33: -0.29460064 | I33: 0.46042668 | J33: 0.24633319 | K33: 0.03692701 | L33: 0.00082177907 | M33: 0.028666689 | N33: 0.018
A34: 1 | B34: 1.1530591 | C34: -0.18041984 | D34: -0.095223919 | E34: 1.859931 | F34: -1.4331468 | G34: -0.90637126 | H34: -0.35482194 | I34: 0.62882002 | J34: 0.27605596 | K34: 0.052117729 | L34: 0.0013559434 | M34: 0.036823136 | N34: 0.024
A35: 1.0000001 | B35: 3.3895933 | C35: -0.4952663 | D35: -0.010879785 | E35: 5.0230087 | F35: -4.3385477 | G35: -4.3422729 | H35: -0.78635076 | I35: 1.9514985 | J35: 0.42649033 | K35: 0.18272668 | L35: 0.0118298 | M35: 0.10876489 | N35: 0.072977525 | O35: HIGHEST SHARPE RATIO = TANGENT PORTFOLIO
A36: 1.0000003 | B36: 3.7287533 | C36: -0.39886006 | D36: -0.5009231 | E36: 5.080276 | F36: -4.0609613 | G36: -4.8792616 | H36: -0.91687955 | I36: 2.2004892 | J36: 0.55346845 | K36: 0.19389905 | L36: 0.014079174 | M36: 0.1186557 | N36: 0.08
A37: 1.0000001 | B37: 4.6486448 | C37: -0.47687445 | D37: -0.64581373 | E37: 6.230413 | F37: -4.9994773 | G37: -6.2981566 | H37: -1.117614 | I37: 2.7617985 | J37: 0.6525445 | K37: 0.24453539 | L37: 0.022010657 | M37: 0.14835989 | N37: 0.1
M39: Capital Allocation Line
L40: Risk free asset | M40: 0 | N40: =B14 -> 2.1049383e-05
E41: Optimal portfolio for a certain investor | L41: Tangent portfolio | M41: =M35 -> 0.10876489 | N41: =N35 -> 0.072977525
E43: Risk aversion | F43: Weight in the tangent portfolio | G43: expected return | H43: Volatility | L43: alpha
E44: =2*52 -> 104 | F44: =($N$35-$B$14)/(E44*($M$35^2)) -> 0.059299781 | G44: =$B$14 + F44*($N$35-$B$14) -> 0.0043473524 | H44: =F44*$M$35 -> 0.0064497339 | L44: 0 | M44: =$M$35*L44 -> 0 | N44: =$B$14+L44*($N$35-$B$14) -> 2.1049383e-05
E45: =3*52 -> 156 | F45: =($N$35-$B$14)/(E45*($M$35^2)) -> 0.039533187 | G45: =$B$14 + F45*($N$35-$B$14) -> 0.0029052514 | H45: =F45*$M$35 -> 0.0042998226 | L45: 0.25 | M45: =$M$35*L45 -> 0.027191222 | N45: =$B$14+L45*($N$35-$B$14) -> 0.018260168
E46: =4*52 -> 208 | F46: =($N$35-$B$14)/(E46*($M$35^2)) -> 0.02964989 | G46: =$B$14 + F46*($N$35-$B$14) -> 0.0021842009 | H46: =F46*$M$35 -> 0.0032248669 | L46: 0.5 | M46: =$M$35*L46 -> 0.054382443 | N46: =$B$14+L46*($N$35-$B$14) -> 0.036499287
E47: =5*52 -> 260 | F47: =($N$35-$B$14)/(E47*($M$35^2)) -> 0.023719912 | G47: =$B$14 + F47*($N$35-$B$14) -> 0.0017515706 | H47: =F47*$M$35 -> 0.0025798936 | L47: 0.75 | M47: =$M$35*L47 -> 0.081573665 | N47: =$B$14+L47*($N$35-$B$14) -> 0.054738406
L48: 1 | M48: =$M$35*L48 -> 0.10876489 | N48: =$B$14+L48*($N$35-$B$14) -> 0.072977525
L49: 1.25 | M49: =$M$35*L49 -> 0.13595611 | N49: =$B$14+L49*($N$35-$B$14) -> 0.091216644
L50: 1.5 | M50: =$M$35*L50 -> 0.16314733 | N50: =$B$14+L50*($N$35-$B$14) -> 0.10945576
A52: CONCLUSION
A53: Efficient Frontier
A54: The efficient frontier represents the set of portfolios offering the highest expected return for a given level of risk, based on the estimated expected returns and covariance matrix of the selected assets.
A55: Each point on the efficient frontier is obtained by minimizing portfolio variance subject to a target expected return and the constraint that portfolio weights sum to one.
A56: The frontier is upward-sloping and smooth, which confirms the internal consistency of the calculations and the positive-definiteness of the covariance matrix. Several portfolios were computed
A57: along the frontier, allowing a clear visualization of the risk–return trade-off faced by investors.
A59: Global Minimum Variance (GMV) Portfolio
A60: The Global Minimum Variance portfolio corresponds to the portfolio with the lowest achievable volatility among all feasible combinations of assets. It highlights the diversification benefits arising from imperfect
A61: correlations between assets. Compared to individual assets, the GMV portfolio exhibits a significantly lower volatility, confirming the role of covariance in risk reduction.
A63: Tangency (Maximum Sharpe Ratio) Portfolio
A64: The tangency portfolio maximizes the Sharpe ratio and represents the optimal risky portfolio for a mean-variance investor in the presence of a risk-free asset. This portfolio lies on the efficient frontier and
A65: dominates all other risky portfolios in terms of risk-adjusted performance. It serves as the building block for optimal portfolios once investor preferences are introduced.
... A72: are coherent with modern portfolio theory and illustrate the economic intuition behind risk-return trade-offs.

Sheet Explanations
A1: Explanations
A3: 1. Asset Selection and Economic Rationale
A4: The portfolio includes a diversified set of assets spanning equities, fixed income, real assets, commodities, and alternative investments. The objective is to capture different sources of return while benefiting
A5: from imperfect correlations across asset classes.
A7: SPY – US Equity Market
A8: SPY represents the US equity market and serves as a benchmark for developed market equities. It offers strong long-term growth potential but exhibits relatively high volatility, reflecting sensitivity to economic cycles,
A9: monetary policy, and corporate earnings. SPY acts as a core growth asset in the portfolio.
A11: VGK – European Equity Market
A12: VGK provides exposure to developed European equities. Compared to SPY, VGK displays slightly lower expected returns and different cyclical dynamics, influenced by European monetary policy and regional economic
A13: conditions. Including VGK enhances geographical diversification and reduces dependence on a single equity market.
A15: VWO – Emerging Market Equities
A16: VWO captures exposure to emerging market economies. While expected returns are lower in the sample period, VWO exhibits different growth drivers and correlation patterns compared to developed markets. This
... A82: This structure reflects realistic investor objectives and enables meaningful construction of efficient portfolios under different constraints and risk preferences.

Sheet No short sales
A2: Asset | B2: Expected return | C2: Volatility | E2: {=Prices!X25:AH35} -> Correlations | F2: SPY | G2: VGK | H2: VWO | I2: IEF | J2: LQD | K2: TIP | L2: VNQ | M2: GLD | N2: DBC | O2: BTC | Q2: {=Prices!X10:AH20} -> Covariances of monthly returns | R2: SPY | S2: VGK | T2: VWO | U2: IEF | V2: LQD | W2: TIP | X2: VNQ | Y2: GLD | Z2: DBC | AA2: BTC
A3: =Prices!Y$3 -> SPY | B3: =Prices!Y4 -> 0.013353829 | C3: =Prices!Y6 -> 0.047649233 | E3: SPY | F3: 1 | G3: 0.83459353 | H3: 0.68918815 | I3: 0.24578786 | J3: 0.66292545 | K3: 0.58699971 | L3: 0.81607365 | M3: 0.15773993 | N3: 0.41577683 | O3: 0.46096585 | Q3: SPY | R3: 0.0022704494 | S3: 0.0020767105 | T3: 0.0015167281 | U3: 0.00024655077 | V3: 0.0008681289 | W3: 0.00048962367 | X3: 0.0021278402 | Y3: 0.0003152741 | Z3: 0.00097690527 | AA3: 0.0043833924
A4: =Prices!Z$3 -> VGK | B4: =Prices!Z4 -> 0.0084964115 | C4: =Prices!Z6 -> 0.052220983 | E4: VGK | F4: 0 | G4: 1 | H4: 0.77191535 | I4: 0.29140302 | J4: 0.6829457 | K4: 0.56960724 | L4: 0.78772612 | M4: 0.28156056 | N4: 0.48797064 | O4: 0.33456399 | Q4: VGK | R4: 0.0020767105 | S4: 0.002727031 | T4: 0.0018617817 | U4: 0.00032035324 | V4: 0.00098015515 | W4: 0.00052070188 | X4: 0.0022509924 | Y4: 0.0006167478 | Z4: 0.0012565362 | AA4: 0.0034866626
A5: =Prices!AA$3 -> VWO | B5: =Prices!AA4 -> 0.0054307927 | C5: =Prices!AA6 -> 0.046186392 | E5: VWO | F5: 0 | G5: 0 | H5: 1 | I5: 0.21723646 | J5: 0.64189323 | K5: 0.44931846 | L5: 0.61941506 | M5: 0.34539843 | N5: 0.49469495 | O5: 0.25634914 | Q5: VWO | R5: 0.0015167281 | S5: 0.0018617817 | T5: 0.0021331828 | U5: 0.00021122084 | V5: 0.00081478014 | W5: 0.00036327617 | X5: 0.0015654872 | Y5: 0.00066915255 | Z5: 0.0011266468 | AA5: 0.0023628252
A6: =Prices!AB$3 -> IEF | B6: =Prices!AB4 -> -0.00033629338 | C6: =Prices!AB6 -> 0.021051838 | E6: IEF | F6: 0 | G6: 0 | H6: 0 | I6: 1 | J6: 0.78331896 | K6: 0.77027045 | L6: 0.39468054 | M6: 0.3675722 | N6: -0.2883916 | O6: 0.11841452 | Q6: IEF | R6: 0.00024655077 | S6: 0.00032035324 | T6: 0.00021122084 | U6: 0.00044317989 | V6: 0.00045320247 | W6: 0.00028385848 | X6: 0.00045466286 | Y6: 0.00032458125 | Z6: -0.00029937042 | AA6: 0.00049748579
A7: =Prices!AC$3 -> LQD | B7: =Prices!AC4 -> 0.00051088612 | C7: =Prices!AC6 -> 0.027482967 | E7: LQD | F7: 0 | G7: 0 | H7: 0 | I7: 0 | J7: 1 | K7: 0.82397669 | L7: 0.73173725 | M7: 0.38027928 | N7: 0.083179825 | O7: 0.31226977 | Q7: LQD | R7: 0.0008681289 | S7: 0.00098015515 | T7: 0.00081478014 | U7: 0.00045320247 | V7: 0.00075531345 | W7: 0.00039641232 | X7: 0.0011004556 | Y7: 0.00043838635 | Z7: 0.00011272438 | AA7: 0.0017126919
A8: =Prices!AD$3 -> TIP | B8: =Prices!AD4 -> 0.00079045933 | C8: =Prices!AD6 -> 0.017505262 | E8: TIP | F8: 0 | G8: 0 | H8: 0 | I8: 0 | J8: 0 | K8: 1 | L8: 0.66911403 | M8: 0.41945981 | N8: 0.084887187 | O8: 0.34613304 | Q8: TIP | R8: 0.00048962367 | S8: 0.00052070188 | T8: 0.00036327617 | U8: 0.00028385848 | V8: 0.00039641232 | W8: 0.00030643419 | X8: 0.00064094753 | Y8: 0.00030799929 | Z8: 7.3273513e-05 | AA8: 0.0012091978
A9: =Prices!AE$3 -> VNQ | B9: =Prices!AE4 -> 0.0038919991 | C9: =Prices!AE6 -> 0.054720964 | E9: VNQ | F9: 0 | G9: 0 | H9: 0 | I9: 0 | J9: 0 | K9: 0 | L9: 1 | M9: 0.21561573 | N9: 0.35588309 | O9: 0.39827182 | Q9: VNQ | R9: 0.0021278402 | S9: 0.0022509924 | T9: 0.0015654872 | U9: 0.00045466286 | V9: 0.0011004556 | W9: 0.00064094753 | X9: 0.0029943839 | Y9: 0.00049490851 | Z9: 0.00096027881 | AA9: 0.0043492964
A10: =Prices!AF$3 -> GLD | B10: =Prices!AF4 -> 0.01496557 | C10: =Prices!AF6 -> 0.041946019 | E10: GLD | F10: 0 | G10: 0 | H10: 0 | I10: 0 | J10: 0 | K10: 0 | L10: 0 | M10: 1 | N10: 0.035311692 | O10: 0.13211006 | Q10: GLD | R10: 0.0003152741 | S10: 0.0006167478 | T10: 0.00066915255 | U10: 0.00032458125 | V10: 0.00043838635 | W10: 0.00030799929 | X10: 0.00049490851 | Y10: 0.0017594685 | Z10: 7.3037439e-05 | AA10: 0.001105891
A11: =Prices!AG$3 -> DBC | B11: =Prices!AG4 -> 0.0060828471 | C11: =Prices!AG6 -> 0.049310143 | E11: DBC | F11: 0 | G11: 0 | H11: 0 | I11: 0 | J11: 0 | K11: 0 | L11: 0 | M11: 0 | N11: 1 | O11: 0.10625791 | Q11: DBC | R11: 0.00097690527 | S11: 0.0012565362 | T11: 0.0011266468 | U11: -0.00029937042 | V11: 0.00011272438 | W11: 7.3273513e-05 | X11: 0.00096027881 | Y11: 7.3037439e-05 | Z11: 0.0024314902 | AA11: 0.0010456425
A12: =Prices!AH$3 -> BTC | B12: =Prices!AH4 -> 0.057898273 | C12: =Prices!AG6 -> 0.049310143 | E12: BTC | F12: 0 | G12: 0 | H12: 0 | I12: 0 | J12: 0 | K12: 0 | L12: 0 | M12: 0 | N12: 0 | O12: 1 | Q12: BTC | R12: 0.0043833924 | S12: 0.0034866626 | T12: 0.0023628252 | U12: 0.00049748579 | V12: 0.0017126919 | W12: 0.0012091978 | X12: 0.0043492964 | Y12: 0.001105891 | Z12: 0.0010456425 | AA12: 0.03982643
A13: ='Efficient Frontier & Specific '!$A$14 -> Fama/French 3 Factors (Monthly) | B13: ='Efficient Frontier & Specific '!$B$14 -> 2.1049383e-05
U14: With short sales
A20: COMPUTATIONS using solver
A21: Sum of weights | B21: w1 | C21: w2 | D21: w3 | E21: w4 | F21: w5 | G21: w6 | H21: w7 | I21: w8 | J21: w9 | K21: w10 | L21: variance | M21: volatility | N21: Expected return | O21: Target Expected return | P21: Sharpe ratio
A22: =SUM(B22:K22) -> 1 | B22: 0 | C22: 0 | D22: 0 | E22: 0.96778913 | F22: 0 | G22: 0.032210881 | H22: 0 | I22: 0 | J22: 0 | K22: 0 | L22: {=MMULT(MMULT(B22:K22,R3:AA12),TRANSPOSE(B22:K22))} -> 0.00043310486 | M22: =SQRT(L22) -> 0.020811171 | N22: {=MMULT(B22:K22,B3:B12)} -> -0.00029999968 | O22: -0.0003 | P22: =(N22-B13)/M22 -> -0.015426766
A25: PORTFOLIOS with no short sales allowed
A26: Sum of weights
A27: 1 | B27: 0 | C27: 0 | D27: 0 | E27: 0.96778913 | F27: 0 | G27: 0.032210881 | H27: 0 | I27: 0 | J27: 0 | K27: 0 | L27: 0.00043310486 | M27: 0.020811171 | N27: -0.00029999968
A28: 1 | B28: 0 | C28: 0 | D28: 0 | E28: 0.4273719 | F28: 0 | G28: 0.4420475 | H28: 0 | I28: 0 | J28: 0.1305806 | K28: 0 | L28: 0.00026458232 | M28: 0.016265987 | N28: 0.0010000001
A29: 1 | B29: 0 | C29: 0 | D29: 0 | E29: 0.40171067 | F29: 0 | G29: 0.45404701 | H29: 0 | I29: 0 | J29: 0.14424236 | K29: 0 | L29: 0.00026373345 | M29: 0.016239872 | N29: 0.0011012173 | O29: GLOBAL MINIMUM VARIANCE PORTFOLIO
A30: 1 | B30: 0.089169407 | C30: 0 | D30: 0 | E30: 0.40595257 | F30: 0 | G30: 0 | H30: 0 | I30: 0.29982821 | J30: 0.18167107 | K30: 0.023378743 | L30: 0.00051255233 | M30: 0.022639619 | N30: 0.0080000001 | U30: Without short sales
A31: 0.99999999 | B31: 0.23002046 | C31: 0 | D31: 0 | E31: 0 | F31: 0 | G31: 0 | H31: 0 | I31: 0.62542734 | J31: 0.065990321 | K31: 0.078561867 | L31: 0.0014690943 | M31: 0.038328765 | N31: 0.017381536 | O31: HIGHEST SHARPE RATIO = TANGENT PORTFOLIO
A32: 1 | B32: 0 | C32: 0 | D32: 0 | E32: 0 | F32: 0 | G32: 0 | H32: 0 | I32: 0.69639815 | J32: 0 | K32: 0.30360185 | L32: 0.0049918868 | M32: 0.070653286 | N32: 0.028000018
A33: 0.99999998 | B33: 0 | C33: 0 | D33: 0 | E33: 0 | F33: 0 | G33: 0 | H33: 0 | I33: 0.46347522 | J33: 0 | K33: 0.53652476 | L33: 0.012392334 | M33: 0.11132086 | N33: 0.038000028
A34: 0.99999998 | B34: 0 | C34: 0 | D34: 0 | E34: 0 | F34: 0 | G34: 0 | H34: 0 | I34: 0.23055231 | J34: 0 | K34: 0.76944767 | L34: 0.024065115 | M34: 0.15512935 | N34: 0.048000038
A35: 1 | B35: 0 | C35: 0 | D35: 0 | E35: 0 | F35: 0 | G35: 0 | H35: 0 | I35: 0.18396869 | J35: 0 | K35: 0.81603131 | L35: 0.026912293 | M35: 0.16404967 | N35: 0.05
M37: Capital Allocation Line
L38: Risk free asset | M38: 0 | N38: =B13 -> 2.1049383e-05
L39: Tangent portfolio | M39: =M31 -> 0.038328765 | N39: =N31 -> 0.017381536
L41: alpha
L42: 0 | M42: =$M$31*L42 -> 0 | N42: =$B$14+L42*($N$31-$B$14) -> 0
L43: 0.25 | M43: =$M$31*L43 -> 0.0095821914 | N43: =$B$14+L43*($N$31-$B$14) -> 0.004345384
L44: 0.5 | M44: =$M$31*L44 -> 0.019164383 | N44: =$B$14+L44*($N$31-$B$14) -> 0.008690768
L45: 0.75 | M45: =$M$31*L45 -> 0.028746574 | N45: =$B$14+L45*($N$31-$B$14) -> 0.013036152
L46: 1 | M46: =$M$31*L46 -> 0.038328765 | N46: =$B$14+L46*($N$31-$B$14) -> 0.017381536
L47: 1.25 | M47: =$M$31*L47 -> 0.047910957 | N47: =$B$14+L47*($N$31-$B$14) -> 0.02172692
L48: 1.5 | M48: =$M$31*L48 -> 0.057493148 | N48: =$B$14+L48*($N$31-$B$14) -> 0.026072304
A49: CONCLUSION | L49: 5.22 | M49: =$M$31*L49 -> 0.20007616 | N49: =$B$14+L49*($N$31-$B$14) -> 0.090731618
A50: Imposing a no-short-sales constraint modifies the shape of the efficient frontier. Compared to the unconstrained case, the constrained frontier is generally less efficient, as the restriction limits
A51: diversification possibilities. Some assets receive zero weights, indicating that they do not contribute optimally under the constraint.
A52: The no-short-sales constraint reduces diversification opportunities and therefore shifts the efficient frontier inward.
A53: The constrained tangency portfolio differs from the unconstrained one, both in composition and performance. This highlights the economic cost of regulatory or institutional constraints and illustrates
A54: how investment restrictions can reduce achievable risk-adjusted returns.

Sheet Changing the data +2% Vol
A2: Asset | B2: Expected return | C2: Volatility | D2: Volatility +2% | F2: {='Efficient Frontier & Specific '!E3:O13} -> Correlations | G2: SPY | H2: VGK | I2: VWO | J2: IEF | K2: LQD | L2: TIP | M2: VNQ | N2: GLD | O2: DBC | P2: BTC | R2: {='Efficient Frontier & Specific '!Q3:AA13} -> Covariances of monthly returns | S2: SPY | T2: VGK | U2: VWO | V2: IEF | W2: LQD | X2: TIP | Y2: VNQ | Z2: GLD | AA2: DBC | AB2: BTC | AD2: NEW Covariances of monthly returns | AE2: SPY | AF2: VGK | AG2: VWO | AH2: IEF | AI2: LQD | AJ2: TIP | AK2: VNQ | AL2: GLD | AM2: DBC | AN2: BTC
A3: =Prices!Y$3 -> SPY | B3: =Prices!Y4 -> 0.013353829 | C3: =Prices!Y6 -> 0.047649233 | D3: =C3*1.02 -> 0.048602217 | F3: SPY | G3: 1 | H3: 0.83459353 | I3: 0.68918815 | J3: 0.24578786 | K3: 0.66292545 | L3: 0.58699971 | M3: 0.81607365 | N3: 0.15773993 | O3: 0.41577683 | P3: 0.46096585 | R3: SPY | S3: 0.0022704494 | T3: 0.0020767105 | U3: 0.0015167281 | V3: 0.00024655077 | W3: 0.0008681289 | X3: 0.00048962367 | Y3: 0.0021278402 | Z3: 0.0003152741 | AA3: 0.00097690527 | AB3: 0.0043833924 | AD3: SPY | AE3: {=INDEX($G$3:$P$12, ROWS($S$3:S3), COLUMNS($S$3:S3)) * INDEX($D$3:$D$12, ROWS($S$3:S3)) * INDEX($D$3:$D$12, COLUMNS($S$3:S3))} -> 0.0023621755 | AF3: {=INDEX($G$3:$P$12, ROWS($S$3:T3), COLUMNS($S$3:T3)) * INDEX($D$3:$D$12, ROWS($S$3:T3)) * INDEX($D$3:$D$12, COLUMNS($S$3:T3))} -> 0.0021606096 | AG3: {=INDEX($G$3:$P$12, ROWS($S$3:U3), COLUMNS($S$3:U3)) * INDEX($D$3:$D$12, ROWS($S$3:U3)) * INDEX($D$3:$D$12, COLUMNS($S$3:U3))} -> 0.001578004 | AH3: {=INDEX($G$3:$P$12, ROWS($S$3:V3), COLUMNS($S$3:V3)) * INDEX($D$3:$D$12, ROWS($S$3:V3)) * INDEX($D$3:$D$12, COLUMNS($S$3:V3))} -> 0.00025651142 | AI3: {=INDEX($G$3:$P$12, ROWS($S$3:W3), COLUMNS($S$3:W3)) * INDEX($D$3:$D$12, ROWS($S$3:W3)) * INDEX($D$3:$D$12, COLUMNS($S$3:W3))} -> 0.00090320131 | AJ3: {=INDEX($G$3:$P$12, ROWS($S$3:X3), COLUMNS($S$3:X3)) * INDEX($D$3:$D$12, ROWS($S$3:X3)) * INDEX($D$3:$D$12, COLUMNS($S$3:X3))} -> 0.00050940447 | AK3: {=INDEX($G$3:$P$12, ROWS($S$3:Y3), COLUMNS($S$3:Y3)) * INDEX($D$3:$D$12, ROWS($S$3:Y3)) * INDEX($D$3:$D$12, COLUMNS($S$3:Y3))} -> 0.0022138049 | AL3: {=INDEX($G$3:$P$12, ROWS($S$3:Z3), COLUMNS($S$3:Z3)) * INDEX($D$3:$D$12, ROWS($S$3:Z3)) * INDEX($D$3:$D$12, COLUMNS($S$3:Z3))} -> 0.00032801117 | ... AN3: {=INDEX($G$3:$P$12, ROWS($S$3:AB3), COLUMNS($S$3:AB3)) * INDEX($D$3:$D$12, ROWS($S$3:AB3)) * INDEX($D$3:$D$12, COLUMNS($S$3:AB3))} -> 0.0011268374
A4: =Prices!Z$3 -> VGK | B4: =Prices!Z4 -> 0.0084964115 | C4: =Prices!Z6 -> 0.052220983 | D4: =C4*1.02 -> 0.053265402 | F4: VGK | G4: 0 | H4: 1 | I4: 0.77191535 | J4: 0.29140302 | K4: 0.6829457 | L4: 0.56960724 | M4: 0.78772612 | N4: 0.28156056 | O4: 0.48797064 | P4: 0.33456399 | R4: VGK | S4: 0.0020767105 | T4: 0.002727031 | U4: 0.0018617817 | V4: 0.00032035324 | W4: 0.00098015515 | X4: 0.00052070188 | Y4: 0.0022509924 | Z4: 0.0006167478 | AA4: 0.0012565362 | AB4: 0.0034866626 | AD4: VGK | AE4: =AF$3 -> 0.0021606096 | AF4: {=INDEX($G$3:$P$12, ROWS($S$3:T4), COLUMNS($S$3:T4)) * INDEX($D$3:$D$12, ROWS($S$3:T4)) * INDEX($D$3:$D$12, COLUMNS($S$3:T4))} -> 0.0028372031 | AG4: {=INDEX($G$3:$P$12, ROWS($S$3:U4), COLUMNS($S$3:U4)) * INDEX($D$3:$D$12, ROWS($S$3:U4)) * INDEX($D$3:$D$12, COLUMNS($S$3:U4))} -> 0.0019369977 | AH4: {=INDEX($G$3:$P$12, ROWS($S$3:V4), COLUMNS($S$3:V4)) * INDEX($D$3:$D$12, ROWS($S$3:V4)) * INDEX($D$3:$D$12, COLUMNS($S$3:V4))} -> 0.00033329551 | AI4: {=INDEX($G$3:$P$12, ROWS($S$3:W4), COLUMNS($S$3:W4)) * INDEX($D$3:$D$12, ROWS($S$3:W4)) * INDEX($D$3:$D$12, COLUMNS($S$3:W4))} -> 0.0010197534 | AJ4: {=INDEX($G$3:$P$12, ROWS($S$3:X4), COLUMNS($S$3:X4)) * INDEX($D$3:$D$12, ROWS($S$3:X4)) * INDEX($D$3:$D$12, COLUMNS($S$3:X4))} -> 0.00054173824 | AK4: {=INDEX($G$3:$P$12, ROWS($S$3:Y4), COLUMNS($S$3:Y4)) * INDEX($D$3:$D$12, ROWS($S$3:Y4)) * INDEX($D$3:$D$12, COLUMNS($S$3:Y4))} -> 0.0023419325 | AL4: {=INDEX($G$3:$P$12, ROWS($S$3:Z4), COLUMNS($S$3:Z4)) * INDEX($D$3:$D$12, ROWS($S$3:Z4)) * INDEX($D$3:$D$12, COLUMNS($S$3:Z4))} -> 0.00064166442 | AM4: {=INDEX($G$3:$P$12, ROWS($S$3:AA4), COLUMNS($S$3:AA4)) * INDEX($D$3:$D$12, ROWS($S$3:AA4)) * INDEX($D$3:$D$12, COLUMNS($S$3:AA4))} -> 0.0013073002 | AN4: {=INDEX($G$3:$P$12, ROWS($S$3:AB4), COLUMNS($S$3:AB4)) * INDEX($D$3:$D$12, ROWS($S$3:AB4)) * INDEX($D$3:$D$12, COLUMNS($S$3:AB4))} -> 0.00089631536
A5: =Prices!AA$3 -> VWO | B5: =Prices!AA4 -> 0.0054307927 | C5: =Prices!AA6 -> 0.046186392 | D5: =C5*1.02 -> 0.047110119 | F5: VWO | G5: 0 | H5: 0 | I5: 1 | J5: 0.21723646 | K5: 0.64189323 | L5: 0.44931846 | M5: 0.61941506 | N5: 0.34539843 | O5: 0.49469495 | P5: 0.25634914 | R5: VWO | S5: 0.0015167281 | T5: 0.0018617817 | U5: 0.0021331828 | V5: 0.00021122084 | W5: 0.00081478014 | X5: 0.00036327617 | Y5: 0.0015654872 | Z5: 0.00066915255 | AA5: 0.0011266468 | AB5: 0.0023628252 | AD5: VWO | AE5: =AG3 -> 0.001578004 | AF5: =AG4 -> 0.0019369977 | AG5: {=INDEX($G$3:$P$12, ROWS($S$3:U5), COLUMNS($S$3:U5)) * INDEX($D$3:$D$12, ROWS($S$3:U5)) * INDEX($D$3:$D$12, COLUMNS($S$3:U5))} -> 0.0022193634 | AH5: {=INDEX($G$3:$P$12, ROWS($S$3:V5), COLUMNS($S$3:V5)) * INDEX($D$3:$D$12, ROWS($S$3:V5)) * INDEX($D$3:$D$12, COLUMNS($S$3:V5))} -> 0.00021975416 | AI5: {=INDEX($G$3:$P$12, ROWS($S$3:W5), COLUMNS($S$3:W5)) * INDEX($D$3:$D$12, ROWS($S$3:W5)) * INDEX($D$3:$D$12, COLUMNS($S$3:W5))} -> 0.00084769726 | AJ5: {=INDEX($G$3:$P$12, ROWS($S$3:X5), COLUMNS($S$3:X5)) * INDEX($D$3:$D$12, ROWS($S$3:X5)) * INDEX($D$3:$D$12, COLUMNS($S$3:X5))} -> 0.00037795253 | AK5: {=INDEX($G$3:$P$12, ROWS($S$3:Y5), COLUMNS($S$3:Y5)) * INDEX($D$3:$D$12, ROWS($S$3:Y5)) * INDEX($D$3:$D$12, COLUMNS($S$3:Y5))} -> 0.0016287329 | AL5: {=INDEX($G$3:$P$12, ROWS($S$3:Z5), COLUMNS($S$3:Z5)) * INDEX($D$3:$D$12, ROWS($S$3:Z5)) * INDEX($D$3:$D$12, COLUMNS($S$3:Z5))} -> 0.00069618631 | AM5: {=INDEX($G$3:$P$12, ROWS($S$3:AA5), COLUMNS($S$3:AA5)) * INDEX($D$3:$D$12, ROWS($S$3:AA5)) * INDEX($D$3:$D$12, COLUMNS($S$3:AA5))} -> 0.0011721633 | AN5: {=INDEX($G$3:$P$12, ROWS($S$3:AB5), COLUMNS($S$3:AB5)) * INDEX($D$3:$D$12, ROWS($S$3:AB5)) * INDEX($D$3:$D$12, COLUMNS($S$3:AB5))} -> 0.00060741079
A6: =Prices!AB$3 -> IEF | B6: =Prices!AB4 -> -0.00033629338 | C6: =Prices!AB6 -> 0.021051838 | D6: =C6*1.02 -> 0.021472875 | F6: IEF | G6: 0 | H6: 0 | I6: 0 | J6: 1 | K6: 0.78331896 | L6: 0.77027045 | M6: 0.39468054 | N6: 0.3675722 | O6: -0.2883916 | P6: 0.11841452 | R6: IEF | S6: 0.00024655077 | T6: 0.00032035324 | U6: 0.00021122084 | V6: 0.00044317989 | W6: 0.00045320247 | X6: 0.00028385848 | Y6: 0.00045466286 | Z6: 0.00032458125 | AA6: -0.00029937042 | AB6: 0.00049748579 | AD6: IEF | AE6: =AH3 -> 0.00025651142 | AF6: =AH4 -> 0.00033329551 | AG6: =AH5 -> 0.00021975416 | AH6: {=INDEX($G$3:$P$12, ROWS($S$3:V6), COLUMNS($S$3:V6)) * INDEX($D$3:$D$12, ROWS($S$3:V6)) * INDEX($D$3:$D$12, COLUMNS($S$3:V6))} -> 0.00046108436 | AI6: {=INDEX($G$3:$P$12, ROWS($S$3:W6), COLUMNS($S$3:W6)) * INDEX($D$3:$D$12, ROWS($S$3:W6)) * INDEX($D$3:$D$12, COLUMNS($S$3:W6))} -> 0.00047151185 | AJ6: {=INDEX($G$3:$P$12, ROWS($S$3:X6), COLUMNS($S$3:X6)) * INDEX($D$3:$D$12, ROWS($S$3:X6)) * INDEX($D$3:$D$12, COLUMNS($S$3:X6))} -> 0.00029532636 | AK6: {=INDEX($G$3:$P$12, ROWS($S$3:Y6), COLUMNS($S$3:Y6)) * INDEX($D$3:$D$12, ROWS($S$3:Y6)) * INDEX($D$3:$D$12, COLUMNS($S$3:Y6))} -> 0.00047303123 | AL6: {=INDEX($G$3:$P$12, ROWS($S$3:Z6), COLUMNS($S$3:Z6)) * INDEX($D$3:$D$12, ROWS($S$3:Z6)) * INDEX($D$3:$D$12, COLUMNS($S$3:Z6))} -> 0.00033769433 | AM6: {=INDEX($G$3:$P$12, ROWS($S$3:AA6), COLUMNS($S$3:AA6)) * INDEX($D$3:$D$12, ROWS($S$3:AA6)) * INDEX($D$3:$D$12, COLUMNS($S$3:AA6))} -> -0.00031146499 | AN6: {=INDEX($G$3:$P$12, ROWS($S$3:AB6), COLUMNS($S$3:AB6)) * INDEX($D$3:$D$12, ROWS($S$3:AB6)) * INDEX($D$3:$D$12, COLUMNS($S$3:AB6))} -> 0.00012788853
A7: =Prices!AC$3 -> LQD | B7: =Prices!AC4 -> 0.00051088612 | C7: =Prices!AC6 -> 0.027482967 | D7: =C7*1.02 -> 0.028032626 | F7: LQD | G7: 0 | H7: 0 | I7: 0 | J7: 0 | K7: 1 | L7: 0.82397669 | M7: 0.73173725 | N7: 0.38027928 | O7: 0.083179825 | P7: 0.31226977 | R7: LQD | S7: 0.0008681289 | T7: 0.00098015515 | U7: 0.00081478014 | V7: 0.00045320247 | W7: 0.00075531345 | X7: 0.00039641232 | Y7: 0.0011004556 | Z7: 0.00043838635 | AA7: 0.00011272438 | AB7: 0.0017126919 | AD7: LQD | AE7: =AI3 -> 0.00090320131 | AF7: =AI4 -> 0.0010197534 | AG7: =AI5 -> 0.00084769726 | AH7: =AI6 -> 0.00047151185 | AI7: {=INDEX($G$3:$P$12, ROWS($S$3:W7), COLUMNS($S$3:W7)) * INDEX($D$3:$D$12, ROWS($S$3:W7)) * INDEX($D$3:$D$12, COLUMNS($S$3:W7))} -> 0.00078582812 | AJ7: {=INDEX($G$3:$P$12, ROWS($S$3:X7), COLUMNS($S$3:X7)) * INDEX($D$3:$D$12, ROWS($S$3:X7)) * INDEX($D$3:$D$12, COLUMNS($S$3:X7))} -> 0.00041242738 | AK7: {=INDEX($G$3:$P$12, ROWS($S$3:Y7), COLUMNS($S$3:Y7)) * INDEX($D$3:$D$12, ROWS($S$3:Y7)) * INDEX($D$3:$D$12, COLUMNS($S$3:Y7))} -> 0.001144914 | AL7: {=INDEX($G$3:$P$12, ROWS($S$3:Z7), COLUMNS($S$3:Z7)) * INDEX($D$3:$D$12, ROWS($S$3:Z7)) * INDEX($D$3:$D$12, COLUMNS($S$3:Z7))} -> 0.00045609716 | AM7: {=INDEX($G$3:$P$12, ROWS($S$3:AA7), COLUMNS($S$3:AA7)) * INDEX($D$3:$D$12, ROWS($S$3:AA7)) * INDEX($D$3:$D$12, COLUMNS($S$3:AA7))} -> 0.00011727845 | AN7: {=INDEX($G$3:$P$12, ROWS($S$3:AB7), COLUMNS($S$3:AB7)) * INDEX($D$3:$D$12, ROWS($S$3:AB7)) * INDEX($D$3:$D$12, COLUMNS($S$3:AB7))} -> 0.00044028122
A8: =Prices!AD$3 -> TIP | B8: =Prices!AD4 -> 0.00079045933 | C8: =Prices!AD6 -> 0.017505262 | D8: =C8*1.02 -> 0.017855367 | F8: TIP | G8: 0 | H8: 0 | I8: 0 | J8: 0 | K8: 0 | L8: 1 | M8: 0.66911403 | N8: 0.41945981 | O8: 0.084887187 | P8: 0.34613304 | R8: TIP | S8: 0.00048962367 | T8: 0.00052070188 | U8: 0.00036327617 | V8: 0.00028385848 | W8: 0.00039641232 | X8: 0.00030643419 | Y8: 0.00064094753 | Z8: 0.00030799929 | AA8: 7.3273513e-05 | AB8: 0.0012091978 | AD8: TIP | AE8: =AJ3 -> 0.00050940447 | AF8: =AJ4 -> 0.00054173824 | AG8: =AJ5 -> 0.00037795253 | AH8: =AJ6 -> 0.00029532636 | AI8: =AJ7 -> 0.00041242738 | AJ8: {=INDEX($G$3:$P$12, ROWS($S$3:X8), COLUMNS($S$3:X8)) * INDEX($D$3:$D$12, ROWS($S$3:X8)) * INDEX($D$3:$D$12, COLUMNS($S$3:X8))} -> 0.00031881413 | AK8: {=INDEX($G$3:$P$12, ROWS($S$3:Y8), COLUMNS($S$3:Y8)) * INDEX($D$3:$D$12, ROWS($S$3:Y8)) * INDEX($D$3:$D$12, COLUMNS($S$3:Y8))} -> 0.00066684182 | AL8: {=INDEX($G$3:$P$12, ROWS($S$3:Z8), COLUMNS($S$3:Z8)) * INDEX($D$3:$D$12, ROWS($S$3:Z8)) * INDEX($D$3:$D$12, COLUMNS($S$3:Z8))} -> 0.00032044246 | AM8: {=INDEX($G$3:$P$12, ROWS($S$3:AA8), COLUMNS($S$3:AA8)) * INDEX($D$3:$D$12, ROWS($S$3:AA8)) * INDEX($D$3:$D$12, COLUMNS($S$3:AA8))} -> 7.6233763e-05 | AN8: {=INDEX($G$3:$P$12, ROWS($S$3:AB8), COLUMNS($S$3:AB8)) * INDEX($D$3:$D$12, ROWS($S$3:AB8)) * INDEX($D$3:$D$12, COLUMNS($S$3:AB8))} -> 0.00031084814
A9: =Prices!AE$3 -> VNQ | B9: =Prices!AE4 -> 0.0038919991 | C9: =Prices!AE6 -> 0.054720964 | D9: =C9*1.02 -> 0.055815383 | F9: VNQ | G9: 0 | H9: 0 | I9: 0 | J9: 0 | K9: 0 | L9: 0 | M9: 1 | N9: 0.21561573 | O9: 0.35588309 | P9: 0.39827182 | R9: VNQ | S9: 0.0021278402 | T9: 0.0022509924 | U9: 0.0015654872 | V9: 0.00045466286 | W9: 0.0011004556 | X9: 0.00064094753 | Y9: 0.0029943839 | Z9: 0.00049490851 | AA9: 0.00096027881 | AB9: 0.0043492964 | AD9: VNQ | AE9: =AK3 -> 0.0022138049 | AF9: =AK4 -> 0.0023419325 | AG9: =AK5 -> 0.0016287329 | AH9: =AK6 -> 0.00047303123 | AI9: =AK7 -> 0.001144914 | AJ9: =AK8 -> 0.00066684182 | AK9: {=INDEX($G$3:$P$12, ROWS($S$3:Y9), COLUMNS($S$3:Y9)) * INDEX($D$3:$D$12, ROWS($S$3:Y9)) * INDEX($D$3:$D$12, COLUMNS($S$3:Y9))} -> 0.003115357 | AL9: {=INDEX($G$3:$P$12, ROWS($S$3:Z9), COLUMNS($S$3:Z9)) * INDEX($D$3:$D$12, ROWS($S$3:Z9)) * INDEX($D$3:$D$12, COLUMNS($S$3:Z9))} -> 0.00051490282 | AM9: {=INDEX($G$3:$P$12, ROWS($S$3:AA9), COLUMNS($S$3:AA9)) * INDEX($D$3:$D$12, ROWS($S$3:AA9)) * INDEX($D$3:$D$12, COLUMNS($S$3:AA9))} -> 0.00099907408 | AN9: {=INDEX($G$3:$P$12, ROWS($S$3:AB9), COLUMNS($S$3:AB9)) * INDEX($D$3:$D$12, ROWS($S$3:AB9)) * INDEX($D$3:$D$12, COLUMNS($S$3:AB9))} -> 0.0011180724
A10: =Prices!AF$3 -> GLD | B10: =Prices!AF4 -> 0.01496557 | C10: =Prices!AF6 -> 0.041946019 | D10: =C10*1.02 -> 0.042784939 | F10: GLD | G10: 0 | H10: 0 | I10: 0 | J10: 0 | K10: 0 | L10: 0 | M10: 0 | N10: 1 | O10: 0.035311692 | P10: 0.13211006 | R10: GLD | S10: 0.0003152741 | T10: 0.0006167478 | U10: 0.00066915255 | V10: 0.00032458125 | W10: 0.00043838635 | X10: 0.00030799929 | Y10: 0.00049490851 | Z10: 0.0017594685 | AA10: 7.3037439e-05 | AB10: 0.001105891 | AD10: GLD | AE10: =AL3 -> 0.00032801117 | AF10: =AL4 -> 0.00064166442 | AG10: =AL5 -> 0.00069618631 | AH10: =AL6 -> 0.00033769433 | AI10: =AL7 -> 0.00045609716 | AJ10: =AL8 -> 0.00032044246 | AK10: =AL9 -> 0.00051490282 | AL10: {=INDEX($G$3:$P$12, ROWS($S$3:Z10), COLUMNS($S$3:Z10)) * INDEX($D$3:$D$12, ROWS($S$3:Z10)) * INDEX($D$3:$D$12, COLUMNS($S$3:Z10))} -> 0.001830551 | AM10: {=INDEX($G$3:$P$12, ROWS($S$3:AA10), COLUMNS($S$3:AA10)) * INDEX($D$3:$D$12, ROWS($S$3:AA10)) * INDEX($D$3:$D$12, COLUMNS($S$3:AA10))} -> 7.5988152e-05 | AN10: {=INDEX($G$3:$P$12, ROWS($S$3:AB10), COLUMNS($S$3:AB10)) * INDEX($D$3:$D$12, ROWS($S$3:AB10)) * INDEX($D$3:$D$12, COLUMNS($S$3:AB10))} -> 0.00028429108
A11: =Prices!AG$3 -> DBC | B11: =Prices!AG4 -> 0.0060828471 | C11: =Prices!AG6 -> 0.049310143 | D11: =C11*1.02 -> 0.050296346 | F11: DBC | G11: 0 | H11: 0 | I11: 0 | J11: 0 | K11: 0 | L11: 0 | M11: 0 | N11: 0 | O11: 1 | P11: 0.10625791 | R11: DBC | S11: 0.00097690527 | T11: 0.0012565362 | U11: 0.0011266468 | V11: -0.00029937042 | W11: 0.00011272438 | X11: 7.3273513e-05 | Y11: 0.00096027881 | Z11: 7.3037439e-05 | AA11: 0.0024314902 | AB11: 0.0010456425 | AD11: DBC | AE11: =AM3 -> 0.0010163722 | AF11: =AM4 -> 0.0013073002 | AG11: =AM5 -> 0.0011721633 | AH11: =AM6 -> -0.00031146499 | AI11: =AM7 -> 0.00011727845 | AJ11: =AM8 -> 7.6233763e-05 | AK11: =AM9 -> 0.00099907408 | AL11: =AM10 -> 7.5988152e-05 | AM11: {=INDEX($G$3:$P$12, ROWS($S$3:AA11), COLUMNS($S$3:AA11)) * INDEX($D$3:$D$12, ROWS($S$3:AA11)) * INDEX($D$3:$D$12, COLUMNS($S$3:AA11))} -> 0.0025297224 | AN11: {=INDEX($G$3:$P$12, ROWS($S$3:AB11), COLUMNS($S$3:AB11)) * INDEX($D$3:$D$12, ROWS($S$3:AB11)) * INDEX($D$3:$D$12, COLUMNS($S$3:AB11))} -> 0.00026880301
A12: =Prices!AH$3 -> BTC | B12: =Prices!AH4 -> 0.057898273 | C12: =Prices!AG6 -> 0.049310143 | D12: =C12*1.02 -> 0.050296346 | F12: BTC | G12: 0 | H12: 0 | I12: 0 | J12: 0 | K12: 0 | L12: 0 | M12: 0 | N12: 0 | O12: 0 | P12: 1 | R12: BTC | S12: 0.0043833924 | T12: 0.0034866626 | U12: 0.0023628252 | V12: 0.00049748579 | W12: 0.0017126919 | X12: 0.0012091978 | Y12: 0.0043492964 | Z12: 0.001105891 | AA12: 0.0010456425 | AB12: 0.03982643 | AD12: BTC | AE12: =AN3 -> 0.0011268374 | AF12: =AN4 -> 0.00089631536 | AG12: =AN5 -> 0.00060741079 | AH12: =AN6 -> 0.00012788853 | AI12: =AN7 -> 0.00044028122 | AJ12: =AN8 -> 0.00031084814 | AK12: =AN9 -> 0.0011180724 | AL12: =AN10 -> 0.00028429108 | AM12: =AN11 -> 0.00026880301 | AN12: {=INDEX($G$3:$P$12, ROWS($S$3:AB12), COLUMNS($S$3:AB12)) * INDEX($D$3:$D$12, ROWS($S$3:AB12)) * INDEX($D$3:$D$12, COLUMNS($S$3:AB12))} -> 0.0025297224
A13: ='No short sales'!A13 -> Fama/French 3 Factors (Monthly) | B13: ='Efficient Frontier & Specific '!B14 -> 2.1049383e-05
B20: COMPUTATIONS using solver
B21: Sum of weights | C21: w1 | D21: w2 | E21: w3 | F21: w4 | G21: w5 | H21: w6 | I21: w7 | J21: w8 | K21: w9 | L21: w10 | M21: variance | N21: volatility | O21: Expected return | P21: Target Expected return | Q21: Sharpe ratio
B22: =SUM(C22:L22) -> 1 | C22: 0.60492639 | D22: 0.084071756 | E22: -0.05281172 | F22: 2.9559438 | G22: -1.6951634 | H22: -3.3051667 | I22: -0.38615097 | J22: 0.65117723 | K22: 0.35435923 | L22: 1.7888144 | M22: {=MMULT(MMULT(C22:L22,AE3:AN12),TRANSPOSE(C22:L22))} -> 0.0076127813 | N22: =SQRT(M22) -> 0.087251254 | O22: {=MMULT(C22:L22,B3:B12)} -> 0.118 | P22: =11.8% -> 0.118 | Q22: =(O22-B13)/N22 -> 1.3521748
B25: PORTFOLIOS
B26: Sum of weights
B27: 1 | C27: 0.028092207 | D27: -0.089062024 | E27: 0.084911272 | F27: 0.45362712 | G27: -0.28746462 | H27: 0.87821619 | I27: -0.11141885 | J27: -0.062412382 | K27: 0.15855468 | L27: -0.053043588 | M27: 0.00020951371 | N27: 0.014474588 | O27: -0.0030000001
B28: 1 | C28: 0.042393889 | D28: -0.084769503 | E28: 0.081496575 | F28: 0.51566788 | G28: -0.32236606 | H28: 0.77449579 | I28: -0.11823034 | J28: -0.044720012 | K28: 0.16340943 | L28: -0.0073776526 | M28: 0.00019143215 | N28: 0.013835901 | O28: 2.9799354e-09
B29: 1 | C29: 0.060465002 | D29: -0.079345262 | E29: 0.077181716 | F29: 0.594059 | G29: -0.36646561 | H29: 0.64343875 | I29: -0.12683841 | J29: -0.022364425 | K29: 0.16954326 | L29: 0.050325973 | M29: 0.00018324693 | N29: 0.013536873 | O29: 0.0037908004 | P29: GMVP +2%VOLA
B30: 1 | C30: 0.080531591 | D30: -0.073322638 | E30: 0.072390967 | F30: 0.68110992 | G30: -0.41543701 | H30: 0.49790915 | I30: -0.13639449 | J30: 0.0024594317 | K30: 0.17635503 | L30: 0.11439807 | M30: 0.00019333832 | N30: 0.013904615 | O30: 0.0080000002
B31: 0.99999999 | C31: 0.12820349 | D31: -0.059013648 | E31: 0.06100886 | F31: 0.88791178 | G31: -0.53177623 | H31: 0.15217689 | I31: -0.15909977 | J31: 0.061433688 | K31: 0.19253716 | L31: 0.26661777 | M31: 0.00029824657 | N31: 0.017269817 | O31: 0.018
B32: 1 | C32: 0.17587586 | D32: -0.044704756 | E32: 0.049626735 | F32: 1.0947154 | G32: -0.64811443 | H32: -0.19355873 | I32: -0.1818051 | J32: 0.12040806 | K32: 0.20871953 | L32: 0.41883738 | M32: 0.00051707215 | N32: 0.022739221 | O32: 0.028
B33: 1 | C33: 0.2246223 | D33: -0.032642414 | E33: 0.039059952 | F33: 1.302542 | G33: -0.76464722 | H33: -0.54064995 | I33: -0.20398517 | J33: 0.17963088 | K33: 0.22510092 | L33: 0.57096867 | M33: 0.00084981908 | N33: 0.029151657 | O33: 0.038000028
B34: =SUM(C34:L34) -> 1 | C34: 0.27121991 | D34: -0.016087794 | E34: 0.026863029 | F34: 1.5083208 | G34: -0.88079292 | H34: -0.88502467 | I34: -0.22721526 | J34: 0.2383566 | K34: 0.2410834 | L34: 0.72327686 | M34: 0.0012964752 | N34: 0.0360066 | O34: 0.048
B35: 1 | C35: 0.32294947 | D35: -0.01581605 | E35: 0.026881175 | F35: 1.7223669 | G35: -1.00894 | H35: -1.2327131 | I35: -0.24417705 | J35: 0.29746789 | K35: 0.25660907 | L35: 0.87537173 | M35: 0.001857206 | N35: 0.043095313 | O35: 0.058
B36: 1 | C36: 0.5102566 | D36: 0.055639556 | E36: -0.030207652 | F36: 2.5452278 | G36: -1.4641105 | H36: -2.6185264 | I36: -0.34104625 | J36: 0.53405164 | K36: 0.32222143 | L36: 1.4864938 | M36: 0.0052534938 | N36: 0.07248099 | O36: 0.098139273 | P36: TANGENT PORTFOLIO
B37: 1 | C37: 0.60492639 | D37: 0.084071756 | E37: -0.05281172 | F37: 2.9559438 | G37: -1.6951634 | H37: -3.3051667 | I37: -0.38615097 | J37: 0.65117723 | K37: 0.35435923 | L37: 1.7888144 | M37: 0.0076127813 | N37: 0.087251254 | O37: 0.118
N39: Capital Allocation Line
M40: Risk free asset | N40: 0 | O40: =B13 -> 2.1049383e-05
M41: Tangent portfolio | N41: =N36 -> 0.07248099 | O41: =O36 -> 0.098139273
M43: alpha
M44: 0 | N44: =$N$36*M44 -> 0 | O44: =$B$14+M44*($O$36-$B$14) -> 0
M45: 0.25 | N45: =$N$36*M45 -> 0.018120247 | O45: =$B$14+M45*($O$36-$B$14) -> 0.024534818
M46: 0.5 | N46: =$N$36*M46 -> 0.036240495 | O46: =$B$14+M46*($O$36-$B$14) -> 0.049069637
M47: 0.75 | N47: =$N$36*M47 -> 0.054360742 | O47: =$B$14+M47*($O$36-$B$14) -> 0.073604455
M48: 1 | N48: =$N$36*M48 -> 0.07248099 | O48: =$B$14+M48*($O$36-$B$14) -> 0.098139273
M49: 1.25 | N49: =$N$36*M49 -> 0.090601237 | O49: =$B$14+M49*($O$36-$B$14) -> 0.12267409
M50: 1.5 | N50: =$N$36*M50 -> 0.10872148 | O50: =$B$14+M50*($O$36-$B$14) -> 0.14720891
B53: CONCLUSION
B54: Increasing asset volatility by 2% leads to an outward shift of the efficient frontier in the risk dimension. For a given expected return, portfolio volatility is higher than in the base case. This confirms the sensitivity of
B55: portfolio outcomes to changes in input parameters.
B57: Comparisons with the base case show that both the GMV and tangency portfolios are affected, with higher overall risk levels and potentially lower Sharpe ratios. Compared to the base case, portfolios now achieve the same return at a higher level of risk.
B58: This exercise underlines the importance of parameter estimation and robustness analysis in portfolio construction.

Sheet Diversity 9 assets
A1: Efficient Frontier (9 assets, No SGLN)
A3: Asset | B3: Expected return | C3: Volatility | E3: {='Changing the data +2% Vol'!F2:O11} -> Correlations | F3: SPY | G3: VGK | H3: VWO | I3: IEF | J3: LQD | K3: TIP | L3: VNQ | M3: GLD | N3: DBC | P3: {='Changing the data +2% Vol'!R2:AA11} -> Covariances of monthly returns | Q3: SPY | R3: VGK | S3: VWO | T3: IEF | U3: LQD | V3: TIP | W3: VNQ | X3: GLD | Y3: DBC | AA3: {=Prices!AJ10:AR19} -> Sylvester's criterion | AB3: 0 | AC3: 0 | AD3: 0 | AE3: 0 | AF3: 0 | AG3: 0 | AH3: 0 | AI3: 0
A4: SPY | B4: 0.013353829 | C4: 0.047649233 | E4: SPY | F4: 1 | G4: 0.83459353 | H4: 0.68918815 | I4: 0.24578786 | J4: 0.66292545 | K4: 0.58699971 | L4: 0.81607365 | M4: 0.15773993 | N4: 0.41577683 | P4: SPY | Q4: 0.0022704494 | R4: 0.0020767105 | S4: 0.0015167281 | T4: 0.00024655077 | U4: 0.0008681289 | V4: 0.00048962367 | W4: 0.0021278402 | X4: 0.0003152741 | Y4: 0.00097690527 | AA4: 0.0022704494 | AB4: 0 | AC4: 0 | AD4: 0 | AE4: 0 | AF4: 0 | AG4: 0 | AH4: 0 | AI4: 0
A5: VGK | B5: 0.0084964115 | C5: 0.052220983 | E5: VGK | F5: 0 | G5: 1 | H5: 0.77191535 | I5: 0.29140302 | J5: 0.6829457 | K5: 0.56960724 | L5: 0.78772612 | M5: 0.28156056 | N5: 0.48797064 | P5: VGK | Q5: 0.0020767105 | R5: 0.002727031 | S5: 0.0018617817 | T5: 0.00032035324 | U5: 0.00098015515 | V5: 0.00052070188 | W5: 0.0022509924 | X5: 0.0006167478 | Y5: 0.0012565362 | AA5: 0 | AB5: 1.8788593e-06 | AC5: 0 | AD5: 0 | AE5: 0 | AF5: 0 | AG5: 0 | AH5: 0 | AI5: 0
A6: VWO | B6: 0.0054307927 | C6: 0.046186392 | E6: VWO | F6: 0 | G6: 0 | H6: 1 | I6: 0.21723646 | J6: 0.64189323 | K6: 0.44931846 | L6: 0.61941506 | M6: 0.34539843 | N6: 0.49469495 | P6: VWO | Q6: 0.0015167281 | R6: 0.0018617817 | S6: 0.0021331828 | T6: 0.00021122084 | U6: 0.00081478014 | V6: 0.00036327617 | W6: 0.0015654872 | X6: 0.00066915255 | Y6: 0.0011266468 | AA6: 0 | AB6: 0 | AC6: 1.5931104e-09 | AD6: 0 | AE6: 0 | AF6: 0 | AG6: 0 | AH6: 0 | AI6: 0
A7: IEF | B7: -0.00033629338 | C7: 0.021051838 | E7: IEF | F7: 0 | G7: 0 | H7: 0 | I7: 1 | J7: 0.78331896 | K7: 0.77027045 | L7: 0.39468054 | M7: 0.3675722 | N7: -0.2883916 | P7: IEF | Q7: 0.00024655077 | R7: 0.00032035324 | S7: 0.00021122084 | T7: 0.00044317989 | U7: 0.00045320247 | V7: 0.00028385848 | W7: 0.00045466286 | X7: 0.00032458125 | Y7: -0.00029937042 | AA7: 0 | AB7: 0 | AC7: 0 | AD7: 6.459494e-13 | AE7: 0 | AF7: 0 | AG7: 0 | AH7: 0 | AI7: 0
A8: LQD | B8: 0.00051088612 | C8: 0.027482967 | E8: LQD | F8: 0 | G8: 0 | H8: 0 | I8: 0 | J8: 1 | K8: 0.82397669 | L8: 0.73173725 | M8: 0.38027928 | N8: 0.083179825 | P8: LQD | Q8: 0.0008681289 | R8: 0.00098015515 | S8: 0.00081478014 | T8: 0.00045320247 | U8: 0.00075531345 | V8: 0.00039641232 | W8: 0.0011004556 | X8: 0.00043838635 | Y8: 0.00011272438 | AA8: 0 | AB8: 0 | AC8: 0 | AD8: 0 | AE8: 5.1080238e-17 | AF8: 0 | AG8: 0 | AH8: 0 | AI8: 0
A9: TIP | B9: 0.00079045933 | C9: 0.017505262 | E9: TIP | F9: 0 | G9: 0 | H9: 0 | I9: 0 | J9: 0 | K9: 1 | L9: 0.66911403 | M9: 0.41945981 | N9: 0.084887187 | P9: TIP | Q9: 0.00048962367 | R9: 0.00052070188 | S9: 0.00036327617 | T9: 0.00028385848 | U9: 0.00039641232 | V9: 0.00030643419 | W9: 0.00064094753 | X9: 0.00030799929 | Y9: 7.3273513e-05 | AA9: 0 | AB9: 0 | AC9: 0 | AD9: 0 | AE9: 0 | AF9: 3.6643133e-21 | AG9: 0 | AH9: 0 | AI9: 0
A10: VNQ | B10: 0.0038919991 | C10: 0.054720964 | E10: VNQ | F10: 0 | G10: 0 | H10: 0 | I10: 0 | J10: 0 | K10: 0 | L10: 1 | M10: 0.21561573 | N10: 0.35588309 | P10: VNQ | Q10: 0.0021278402 | R10: 0.0022509924 | S10: 0.0015654872 | T10: 0.00045466286 | U10: 0.0011004556 | V10: 0.00064094753 | W10: 0.0029943839 | X10: 0.00049490851 | Y10: 0.00096027881 | AA10: 0 | AB10: 0 | AC10: 0 | AD10: 0 | AE10: 0 | AF10: 0 | AG10: 2.6255843e-24 | AH10: 0 | AI10: 0
A11: GLD | B11: 0.01496557 | C11: 0.041946019 | E11: GLD | F11: 0 | G11: 0 | H11: 0 | I11: 0 | J11: 0 | K11: 0 | L11: 0 | M11: 1 | N11: 0.035311692 | P11: GLD | Q11: 0.0003152741 | R11: 0.0006167478 | S11: 0.00066915255 | T11: 0.00032458125 | U11: 0.00043838635 | V11: 0.00030799929 | W11: 0.00049490851 | X11: 0.0017594685 | Y11: 7.3037439e-05 | AA11: 0 | AB11: 0 | AC11: 0 | AD11: 0 | AE11: 0 | AF11: 0 | AG11: 0 | AH11: 3.2937397e-27 | AI11: 0
A12: DBC | B12: 0.0060828471 | C12: 0.049310143 | E12: DBC | F12: 0 | G12: 0 | H12: 0 | I12: 0 | J12: 0 | K12: 0 | L12: 0 | M12: 0 | N12: 1 | P12: DBC | Q12: 0.00097690527 | R12: 0.0012565362 | S12: 0.0011266468 | T12: -0.00029937042 | U12: 0.00011272438 | V12: 7.3273513e-05 | W12: 0.00096027881 | X12: 7.3037439e-05 | Y12: 0.0024314902 | AA12: 0 | AB12: 0 | AC12: 0 | AD12: 0 | AE12: 0 | AF12: 0 | AG12: 0 | AH12: 0 | AI12: 3.886177e-30
A14: ='Changing the data +2% Vol'!A13 -> Fama/French 3 Factors (Monthly) | B14: ='Changing the data +2% Vol'!B13 -> 2.1049383e-05
A17: COMPUTATIONS using solver
A18: Sum of weights | B18: w1 | C18: w2 | D18: w3 | E18: w4 | F18: w5 | G18: w6 | H18: w7 | I18: w8 | J18: w9 | K18: variance | L18: volatility | M18: Expected return | N18: Target Expected return | O18: Sharpe ratio
A19: =SUM(B19:J19) -> 1.0000001 | B19: 4.9799422 | C19: -0.57425362 | D19: -0.74502449 | E19: 5.1224232 | F19: -4.5798073 | G19: -5.4655542 | H19: -1.0016776 | I19: 2.7976756 | J19: 0.46627641 | K19: {=MMULT(MMULT(B19:J19,Q4:Y12),TRANSPOSE(B19:J19))} -> 0.019365562 | L19: =SQRT(K19) -> 0.1391602 | M19: {=MMULT(B19:J19,B4:B12)} -> 0.090000001 | N19: 0.09 | O19: =(M19-B14)/L19 -> 0.64658537
A22: PORTFOLIOS
A23: Sum of weights
A24: 1 | B24: -0.0040702462 | C24: -0.079231514 | D24: 0.089108026 | E24: 0.48026208 | F24: -0.28598479 | G24: 0.81924356 | H24: -0.11061063 | I24: -0.069924694 | J24: 0.16120822 | K24: 0.00018722335 | L24: 0.013682958 | M24: -0.00040000001
A25: 0.99999906 | B25: 0.085694527 | C25: -0.088147305 | D25: 0.074084023 | E25: 0.56386766 | F25: -0.36331684 | G25: 0.70605183 | H25: -0.12665973 | I25: -0.018277888 | J25: 0.16670278 | K25: 0.0001807694 | L25: 0.013445051 | M25: 0.001228145 | N25: GMVP
A26: 1 | B26: 0.13927501 | C26: -0.093468653 | D26: 0.065117829 | E26: 0.61377454 | F26: -0.40948085 | G26: 0.63848839 | H26: -0.13623864 | I26: 0.012550586 | J26: 0.1699818 | K26: 0.00018306903 | L26: 0.013530301 | M26: 0.0022
A27: 1 | B27: 0.19440755 | C27: -0.098946168 | D27: 0.055891777 | E27: 0.66512397 | F27: -0.45697766 | G27: 0.56896567 | H27: -0.14609283 | I27: 0.04427233 | J27: 0.17335535 | K27: 0.00019023535 | L27: 0.013792583 | M27: 0.0032
A28: 1 | B28: 0.24954097 | C28: -0.10442064 | D28: 0.046663269 | E28: 0.71647861 | F28: -0.50447576 | G28: 0.49944155 | H28: -0.15595258 | I28: 0.075993091 | J28: 0.17673149 | K28: 0.00020227063 | L28: 0.014222188 | M28: 0.0042
A29: 1 | B29: 0.35980671 | C29: -0.11537246 | D29: 0.028209258 | E29: 0.81917977 | F29: -0.59947284 | G29: 0.36039999 | H29: -0.17566635 | I29: 0.13943547 | J29: 0.18348047 | K29: 0.00024094811 | L29: 0.015522503 | M29: 0.0062
A30: 1 | B30: 0.47007261 | C30: -0.12632433 | D30: 0.009755327 | E30: 0.92188271 | F30: -0.69446991 | G30: 0.22135603 | H30: -0.19538029 | I30: 0.20287826 | J30: 0.1902296 | K30: 0.00029910165 | L30: 0.017294556 | M30: 0.0082000062
A31: 1 | B31: 0.5803383 | C31: -0.13727707 | D31: -0.0086990148 | E31: 1.0245842 | F31: -0.78946533 | G31: 0.082312901 | H31: -0.21509378 | I31: 0.26632066 | J31: 0.1969791 | K31: 0.00037673063 | L31: 0.01940955 | M31: 0.0102
A32: 1.0000001 | B32: 1.0214008 | C32: -0.18108323 | D32: -0.082515921 | E32: 1.4353946 | F32: -1.1694503 | G32: -0.4738627 | H32: -0.29394972 | I32: 0.52009055 | J32: 0.22397601 | K32: 0.00088200603 | L32: 0.029698586 | M32: 0.0182
A33: 0.99999995 | B33: 3.4769152 | C33: -0.42496689 | D33: -0.49347373 | E33: 3.7224877 | F33: -3.2849299 | G33: -3.5702477 | H33: -0.73296396 | I33: 1.9328992 | J33: 0.37428009 | K33: 0.0093915992 | L33: 0.096910264 | M33: 0.062738206 | N33: TANGENT PORTFOLIO
A34: 1.0000001 | B34: 4.9799422 | C34: -0.57425362 | D34: -0.74502449 | E34: 5.1224232 | F34: -4.5798073 | G34: -5.4655542 | H34: -1.0016776 | I34: 2.7976756 | J34: 0.46627641 | K34: 0.019365562 | L34: 0.1391602 | M34: 0.090000001
L37: Capital Allocation Line
K38: Risk free asset | L38: 0 | M38: =B14 -> 2.1049383e-05
K39: Tangent portfolio | L39: =L33 -> 0.096910264 | M39: =M33 -> 0.062738206
K41: alpha
K42: 0 | L42: =$L$39*K42 -> 0 | M42: =$B$14+K42*($M$33-$B$14) -> 2.1049383e-05
K43: 0.25 | L43: =$L$39*K43 -> 0.024227566 | M43: =$B$14+K43*($M$33-$B$14) -> 0.015700338
K44: 0.5 | L44: =$L$39*K44 -> 0.048455132 | M44: =$B$14+K44*($M$33-$B$14) -> 0.031379628
K45: 0.75 | L45: =$L$39*K45 -> 0.072682698 | M45: =$B$14+K45*($M$33-$B$14) -> 0.047058917
K46: 1 | L46: =$L$39*K46 -> 0.096910264 | M46: =$B$14+K46*($M$33-$B$14) -> 0.062738206
K47: 1.25 | L47: =$L$39*K47 -> 0.12113783 | M47: =$B$14+K47*($M$33-$B$14) -> 0.078417495
K48: 1.5 | L48: =$L$39*K48 -> 0.1453654 | M48: =$B$14+K48*($M$33-$B$14) -> 0.094096784
A54: CONCLUSION
A55: Expanding the investment universe to nine assets enhances diversification opportunities. The efficient frontier obtained with a larger asset set dominates the frontier based on fewer assets, particularly at lower
A56: levels of risk. This demonstrates the benefits of diversification when additional assets exhibit imperfect correlations.
A58: The GMV portfolio achieves lower volatility compared to the base case, and the overall efficient frontier becomes more favorable. These results confirm one of the key insights of modern portfolio theory:
A59: increasing the number of diversified assets can improve the risk–return profile of portfolios.
A61: Overall, the results are consistent with modern portfolio theory. Diversification across asset classes significantly improves the risk–return trade-off, while constraints and parameter changes illustrate
A62: the sensitivity of optimal portfolios to investor preferences and market assumptions.
